[
    {
        "log": {
            "access": "",
            "error": "",
            "loglevel": "warning"
        },
        "outbounds": [
            {
                "tag": "proxy",
                "protocol": "vless",
                "settings": {
                    "vnext": [
                        {
                            "address": "2001:41d0:801:1000::1caf",
                            "port": 1152,
                            "users": [
                                {
                                    "id": "dfa25b43-edf2-99e4-c3b0-1aa7c9ccaa96",
                                    "alterId": 0,
                                    "email": "t@t.tt",
                                    "security": "auto",
                                    "encryption": "none",
                                    "flow": "xtls-rprx-vision"
                                }
                            ]
                        }
                    ]
                },
                "streamSettings": {
                    "network": "tcp",
                    "security": "reality",
                    "realitySettings": {
                        "serverName": "www.stackoverflow.com",
                        "fingerprint": "chrome",
                        "show": false,
                        "publicKey": "EsdPQG7EdQ6yCid_OtlMfCDIRTnmFZ_ujpKbaqOiCT4",
                        "shortId": "4374d295a4f9dd83",
                        "spiderX": ""
                    }
                },
                "mux": {
                    "enabled": false,
                    "concurrency": -1
                }
            },
            {
                "tag": "direct",
                "protocol": "freedom",
                "settings": {}
            },
            {
                "tag": "block",
                "protocol": "blackhole",
                "settings": {
                    "response": {
                        "type": "http"
                    }
                }
            }
        ],
        "inbounds": [
            {
                "tag": "socks",
                "port": 10808,
                "listen": "127.0.0.1",
                "protocol": "socks",
                "sniffing": {
                    "enabled": true,
                    "destOverride": [
                        "http",
                        "tls"
                    ],
                    "routeOnly": false
                },
                "settings": {
                    "auth": "noauth",
                    "udp": true,
                    "allowTransparent": false
                }
            },
            {
                "tag": "http",
                "port": 10809,
                "listen": "127.0.0.1",
                "protocol": "http",
                "sniffing": {
                    "enabled": true,
                    "destOverride": [
                        "http",
                        "tls"
                    ],
                    "routeOnly": false
                },
                "settings": {
                    "auth": "noauth",
                    "udp": true,
                    "allowTransparent": false
                }
            }
        ],
        "remarks": "United Kingdom: || OVH SAS"
    },
    {
        "log": {
            "access": "",
            "error": "",
            "loglevel": "warning"
        },
        "outbounds": [
            {
                "tag": "proxy",
                "protocol": "vless",
                "settings": {
                    "vnext": [
                        {
                            "address": "\n<html><head>\n<meta http-equiv=\"content-type\" content=\"text/html;charset=utf-8\">\n<title>403 Forbidden</title>\n</head>\n<body text=#000000 bgcolor=#ffffff>\n<h1>Error: Forbidden</h1>\n<h2>Your client does not have permission to get URL <code>/api/</code> from this server.</h2>\n<h2></h2>\n</body></html>\n",
                            "port": 443,
                            "users": [
                                {
                                    "id": "e8bcc78f-6f92-4aa6-84e5-30db1a0143d6",
                                    "alterId": 0,
                                    "email": "t@t.tt",
                                    "security": "auto",
                                    "encryption": "none",
                                    "flow": ""
                                }
                            ]
                        }
                    ]
                },
                "streamSettings": {
                    "network": "tcp",
                    "security": "reality",
                    "realitySettings": {
                        "serverName": "eset.com",
                        "fingerprint": "chrome",
                        "show": false,
                        "publicKey": "_scshlStWSz3DI8nsre9mq87ZrPP5ov3a0NMuHkvyjU",
                        "shortId": "fc",
                        "spiderX": ""
                    }
                },
                "mux": {
                    "enabled": false,
                    "concurrency": -1
                }
            },
            {
                "tag": "direct",
                "protocol": "freedom",
                "settings": {}
            },
            {
                "tag": "block",
                "protocol": "blackhole",
                "settings": {
                    "response": {
                        "type": "http"
                    }
                }
            }
        ],
        "inbounds": [
            {
                "tag": "socks",
                "port": 10808,
                "listen": "127.0.0.1",
                "protocol": "socks",
                "sniffing": {
                    "enabled": true,
                    "destOverride": [
                        "http",
                        "tls"
                    ],
                    "routeOnly": false
                },
                "settings": {
                    "auth": "noauth",
                    "udp": true,
                    "allowTransparent": false
                }
            },
            {
                "tag": "http",
                "port": 10809,
                "listen": "127.0.0.1",
                "protocol": "http",
                "sniffing": {
                    "enabled": true,
                    "destOverride": [
                        "http",
                        "tls"
                    ],
                    "routeOnly": false
                },
                "settings": {
                    "auth": "noauth",
                    "udp": true,
                    "allowTransparent": false
                }
            }
        ],
        "remarks": "Germany: || Hetzner Online AG"
    },
    {
        "log": {
            "access": "",
            "error": "",
            "loglevel": "warning"
        },
        "outbounds": [
            {
                "tag": "proxy",
                "protocol": "vless",
                "settings": {
                    "vnext": [
                        {
                            "address": "2001:15e8:110:5e3f::1",
                            "port": 43776,
                            "users": [
                                {
                                    "id": "3a053d57-c20a-455a-a21a-95d32f69b24c",
                                    "alterId": 0,
                                    "email": "t@t.tt",
                                    "security": "auto",
                                    "encryption": "none",
                                    "flow": ""
                                }
                            ]
                        }
                    ]
                },
                "streamSettings": {
                    "network": "grpc",
                    "grpcSettings": {
                        "serviceName": "ZEDMODEON-ZEDMODEON-ZEDMODEON-ZEDMODEON-ZEDMODEON-ZEDMODEON-ZEDMODEON-ZEDMODEON-ZEDMODEON-ZEDMODEON-ZEDMODEON-ZEDMODEON-ZEDMODEON-ZEDMODEON-ZEDMODEON-ZEDMODEON?ed=2048",
                        "multiMode": false,
                        "idle_timeout": 60,
                        "health_check_timeout": 20,
                        "permit_without_stream": false,
                        "initial_windows_size": 0
                    }
                },
                "mux": {
                    "enabled": false,
                    "concurrency": -1
                }
            },
            {
                "tag": "direct",
                "protocol": "freedom",
                "settings": {}
            },
            {
                "tag": "block",
                "protocol": "blackhole",
                "settings": {
                    "response": {
                        "type": "http"
                    }
                }
            }
        ],
        "inbounds": [
            {
                "tag": "socks",
                "port": 10808,
                "listen": "127.0.0.1",
                "protocol": "socks",
                "sniffing": {
                    "enabled": true,
                    "destOverride": [
                        "http",
                        "tls"
                    ],
                    "routeOnly": false
                },
                "settings": {
                    "auth": "noauth",
                    "udp": true,
                    "allowTransparent": false
                }
            },
            {
                "tag": "http",
                "port": 10809,
                "listen": "127.0.0.1",
                "protocol": "http",
                "sniffing": {
                    "enabled": true,
                    "destOverride": [
                        "http",
                        "tls"
                    ],
                    "routeOnly": false
                },
                "settings": {
                    "auth": "noauth",
                    "udp": true,
                    "allowTransparent": false
                }
            }
        ],
        "remarks": "Czechia: || INTERNET CZ, a.s."
    },
    {
        "log": {
            "access": "",
            "error": "",
            "loglevel": "warning"
        },
        "outbounds": [
            {
                "tag": "proxy",
                "protocol": "vless",
                "settings": {
                    "vnext": [
                        {
                            "address": "2406:8dc0:6004:3015:4876:def6:b03d:6787",
                            "port": 50126,
                            "users": [
                                {
                                    "id": "459b4a80-bd61-4ecd-a26b-e9c1809d9e45",
                                    "alterId": 0,
                                    "email": "t@t.tt",
                                    "security": "auto",
                                    "encryption": "none",
                                    "flow": "xtls-rprx-vision"
                                }
                            ]
                        }
                    ]
                },
                "streamSettings": {
                    "network": "tcp",
                    "security": "reality",
                    "realitySettings": {
                        "serverName": "www.yahoo.com",
                        "fingerprint": "chrome",
                        "show": false,
                        "publicKey": "qhTzYYIgBzDLNYR79oxftqdo1kzL-1_hGJKfqrOliCY",
                        "shortId": "",
                        "spiderX": ""
                    }
                },
                "mux": {
                    "enabled": false,
                    "concurrency": -1
                }
            },
            {
                "tag": "direct",
                "protocol": "freedom",
                "settings": {}
            },
            {
                "tag": "block",
                "protocol": "blackhole",
                "settings": {
                    "response": {
                        "type": "http"
                    }
                }
            }
        ],
        "inbounds": [
            {
                "tag": "socks",
                "port": 10808,
                "listen": "127.0.0.1",
                "protocol": "socks",
                "sniffing": {
                    "enabled": true,
                    "destOverride": [
                        "http",
                        "tls"
                    ],
                    "routeOnly": false
                },
                "settings": {
                    "auth": "noauth",
                    "udp": true,
                    "allowTransparent": false
                }
            },
            {
                "tag": "http",
                "port": 10809,
                "listen": "127.0.0.1",
                "protocol": "http",
                "sniffing": {
                    "enabled": true,
                    "destOverride": [
                        "http",
                        "tls"
                    ],
                    "routeOnly": false
                },
                "settings": {
                    "auth": "noauth",
                    "udp": true,
                    "allowTransparent": false
                }
            }
        ],
        "remarks": "Taiwan: || AKILE LTD"
    },
    {
        "log": {
            "access": "",
            "error": "",
            "loglevel": "warning"
        },
        "outbounds": [
            {
                "tag": "proxy",
                "protocol": "vless",
                "settings": {
                    "vnext": [
                        {
                            "address": "2a01:4f8:c013:5577::1",
                            "port": 2095,
                            "users": [
                                {
                                    "id": "8dabe69a-0cf2-47d1-bce2-2404bb1d67d5",
                                    "alterId": 0,
                                    "email": "t@t.tt",
                                    "security": "auto",
                                    "encryption": "none",
                                    "flow": ""
                                }
                            ]
                        }
                    ]
                },
                "streamSettings": {
                    "network": "httpupgrade",
                    "httpupgradeSettings": {
                        "path": "/d3d3LmlyYW5ob3N0LmNvbQ==?ed=2560",
                        "host": "mci.mtn.ir.com.org.net.om.org.my-digimento0.ir."
                    }
                },
                "mux": {
                    "enabled": false,
                    "concurrency": -1
                }
            },
            {
                "tag": "direct",
                "protocol": "freedom",
                "settings": {}
            },
            {
                "tag": "block",
                "protocol": "blackhole",
                "settings": {
                    "response": {
                        "type": "http"
                    }
                }
            }
        ],
        "inbounds": [
            {
                "tag": "socks",
                "port": 10808,
                "listen": "127.0.0.1",
                "protocol": "socks",
                "sniffing": {
                    "enabled": true,
                    "destOverride": [
                        "http",
                        "tls"
                    ],
                    "routeOnly": false
                },
                "settings": {
                    "auth": "noauth",
                    "udp": true,
                    "allowTransparent": false
                }
            },
            {
                "tag": "http",
                "port": 10809,
                "listen": "127.0.0.1",
                "protocol": "http",
                "sniffing": {
                    "enabled": true,
                    "destOverride": [
                        "http",
                        "tls"
                    ],
                    "routeOnly": false
                },
                "settings": {
                    "auth": "noauth",
                    "udp": true,
                    "allowTransparent": false
                }
            }
        ],
        "remarks": "Germany: || Hetzner Online GmbH"
    },
    {
        "log": {
            "access": "",
            "error": "",
            "loglevel": "warning"
        },
        "outbounds": [
            {
                "tag": "proxy",
                "protocol": "vless",
                "settings": {
                    "vnext": [
                        {
                            "address": "2a01:e5c0:722f::2",
                            "port": 14703,
                            "users": [
                                {
                                    "id": "19b55d51-0506-4ae1-9583-97e279306905",
                                    "alterId": 0,
                                    "email": "t@t.tt",
                                    "security": "auto",
                                    "encryption": "none",
                                    "flow": ""
                                }
                            ]
                        }
                    ]
                },
                "streamSettings": {
                    "network": "tcp",
                    "tcpSettings": {
                        "header": {
                            "type": "http",
                            "request": {
                                "version": "1.1",
                                "method": "GET",
                                "path": [
                                    "/"
                                ],
                                "headers": {
                                    "Host": [
                                        "analytics.google.com"
                                    ],
                                    "User-Agent": [
                                        ""
                                    ],
                                    "Accept-Encoding": [
                                        "gzip, deflate"
                                    ],
                                    "Connection": [
                                        "keep-alive"
                                    ],
                                    "Pragma": "no-cache"
                                }
                            }
                        }
                    }
                },
                "mux": {
                    "enabled": false,
                    "concurrency": -1
                }
            },
            {
                "tag": "direct",
                "protocol": "freedom",
                "settings": {}
            },
            {
                "tag": "block",
                "protocol": "blackhole",
                "settings": {
                    "response": {
                        "type": "http"
                    }
                }
            }
        ],
        "inbounds": [
            {
                "tag": "socks",
                "port": 10808,
                "listen": "127.0.0.1",
                "protocol": "socks",
                "sniffing": {
                    "enabled": true,
                    "destOverride": [
                        "http",
                        "tls"
                    ],
                    "routeOnly": false
                },
                "settings": {
                    "auth": "noauth",
                    "udp": true,
                    "allowTransparent": false
                }
            },
            {
                "tag": "http",
                "port": 10809,
                "listen": "127.0.0.1",
                "protocol": "http",
                "sniffing": {
                    "enabled": true,
                    "destOverride": [
                        "http",
                        "tls"
                    ],
                    "routeOnly": false
                },
                "settings": {
                    "auth": "noauth",
                    "udp": true,
                    "allowTransparent": false
                }
            }
        ],
        "remarks": "Sweden: || Aeza International LTD"
    },
    {
        "log": {
            "access": "",
            "error": "",
            "loglevel": "warning"
        },
        "outbounds": [
            {
                "tag": "proxy",
                "protocol": "vless",
                "settings": {
                    "vnext": [
                        {
                            "address": "\n<html><head>\n<meta http-equiv=\"content-type\" content=\"text/html;charset=utf-8\">\n<title>403 Forbidden</title>\n</head>\n<body text=#000000 bgcolor=#ffffff>\n<h1>Error: Forbidden</h1>\n<h2>Your client does not have permission to get URL <code>/api/</code> from this server.</h2>\n<h2></h2>\n</body></html>\n",
                            "port": 8081,
                            "users": [
                                {
                                    "id": "55e79d77-c2ea-40ec-b10e-8deb79972c37",
                                    "alterId": 0,
                                    "email": "t@t.tt",
                                    "security": "auto",
                                    "encryption": "none",
                                    "flow": "xtls-rprx-vision"
                                }
                            ]
                        }
                    ]
                },
                "streamSettings": {
                    "network": "tcp",
                    "security": "reality",
                    "realitySettings": {
                        "serverName": "refersion.com",
                        "fingerprint": "chrome",
                        "show": false,
                        "publicKey": "tzwgsCEGbdpNwS3NVwGV7SK0tvJVf4TzTnOUm6fWvGU",
                        "shortId": "bc9fccfc8ebf1dfd",
                        "spiderX": ""
                    }
                },
                "mux": {
                    "enabled": false,
                    "concurrency": -1
                }
            },
            {
                "tag": "direct",
                "protocol": "freedom",
                "settings": {}
            },
            {
                "tag": "block",
                "protocol": "blackhole",
                "settings": {
                    "response": {
                        "type": "http"
                    }
                }
            }
        ],
        "inbounds": [
            {
                "tag": "socks",
                "port": 10808,
                "listen": "127.0.0.1",
                "protocol": "socks",
                "sniffing": {
                    "enabled": true,
                    "destOverride": [
                        "http",
                        "tls"
                    ],
                    "routeOnly": false
                },
                "settings": {
                    "auth": "noauth",
                    "udp": true,
                    "allowTransparent": false
                }
            },
            {
                "tag": "http",
                "port": 10809,
                "listen": "127.0.0.1",
                "protocol": "http",
                "sniffing": {
                    "enabled": true,
                    "destOverride": [
                        "http",
                        "tls"
                    ],
                    "routeOnly": false
                },
                "settings": {
                    "auth": "noauth",
                    "udp": true,
                    "allowTransparent": false
                }
            }
        ],
        "remarks": "Germany: || Hetzner Online GmbH"
    },
    {
        "log": {
            "access": "",
            "error": "",
            "loglevel": "warning"
        },
        "outbounds": [
            {
                "tag": "proxy",
                "protocol": "vless",
                "settings": {
                    "vnext": [
                        {
                            "address": "2607:5300:60:9a68::1",
                            "port": 8443,
                            "users": [
                                {
                                    "id": "57ba2ab1-a283-42eb-82ee-dc3561a805b8",
                                    "alterId": 0,
                                    "email": "t@t.tt",
                                    "security": "auto",
                                    "encryption": "none",
                                    "flow": ""
                                }
                            ]
                        }
                    ]
                },
                "streamSettings": {
                    "network": "ws",
                    "wsSettings": {
                        "path": "/57ba2ab1",
                        "headers": {
                            "Host": "ovhwuxian.pai50288.uk"
                        }
                    },
                    "security": "tls",
                    "tlsSettings": {
                        "allowInsecure": true,
                        "serverName": "ovhwuxian.pai50288.uk",
                        "alpn": []
                    }
                },
                "mux": {
                    "enabled": false,
                    "concurrency": -1
                }
            },
            {
                "tag": "direct",
                "protocol": "freedom",
                "settings": {}
            },
            {
                "tag": "block",
                "protocol": "blackhole",
                "settings": {
                    "response": {
                        "type": "http"
                    }
                }
            }
        ],
        "inbounds": [
            {
                "tag": "socks",
                "port": 10808,
                "listen": "127.0.0.1",
                "protocol": "socks",
                "sniffing": {
                    "enabled": true,
                    "destOverride": [
                        "http",
                        "tls"
                    ],
                    "routeOnly": false
                },
                "settings": {
                    "auth": "noauth",
                    "udp": true,
                    "allowTransparent": false
                }
            },
            {
                "tag": "http",
                "port": 10809,
                "listen": "127.0.0.1",
                "protocol": "http",
                "sniffing": {
                    "enabled": true,
                    "destOverride": [
                        "http",
                        "tls"
                    ],
                    "routeOnly": false
                },
                "settings": {
                    "auth": "noauth",
                    "udp": true,
                    "allowTransparent": false
                }
            }
        ],
        "remarks": "Canada: || OVH SAS"
    },
    {
        "log": {
            "access": "",
            "error": "",
            "loglevel": "warning"
        },
        "outbounds": [
            {
                "tag": "proxy",
                "protocol": "vless",
                "settings": {
                    "vnext": [
                        {
                            "address": "2a12:5940:5fb6::2",
                            "port": 2052,
                            "users": [
                                {
                                    "id": "eb3669aa-9021-4f90-b742-eb2c2b0ac40b",
                                    "alterId": 0,
                                    "email": "t@t.tt",
                                    "security": "auto",
                                    "encryption": "none",
                                    "flow": ""
                                }
                            ]
                        }
                    ]
                },
                "streamSettings": {
                    "network": "httpupgrade",
                    "httpupgradeSettings": {
                        "path": "Telegramjoin:@V2Ray_Rolly-Telegramjoin:@V2Ray_Rolly-Telegramjoin:@V2Ray_Rolly-Telegramjoin:@V2Ray_Rolly-Telegramjoin:@V2Ray_Rolly-Telegramjoin:@V2Ray_Rolly-Telegramjoin:@V2Ray_Rolly-Telegramjoin:@V2Ray_Rolly-Telegramjoin:@V2Ray_Rolly-Telegramjoin:@V2Ray_Rolly-Telegramjoin:@V2Ray_Rolly-",
                        "host": "Bbvghbbhbbgb.yhggggggghhg-cggfgyggyhhggygctggfffdccf.BLOG"
                    }
                },
                "mux": {
                    "enabled": false,
                    "concurrency": -1
                }
            },
            {
                "tag": "direct",
                "protocol": "freedom",
                "settings": {}
            },
            {
                "tag": "block",
                "protocol": "blackhole",
                "settings": {
                    "response": {
                        "type": "http"
                    }
                }
            }
        ],
        "inbounds": [
            {
                "tag": "socks",
                "port": 10808,
                "listen": "127.0.0.1",
                "protocol": "socks",
                "sniffing": {
                    "enabled": true,
                    "destOverride": [
                        "http",
                        "tls"
                    ],
                    "routeOnly": false
                },
                "settings": {
                    "auth": "noauth",
                    "udp": true,
                    "allowTransparent": false
                }
            },
            {
                "tag": "http",
                "port": 10809,
                "listen": "127.0.0.1",
                "protocol": "http",
                "sniffing": {
                    "enabled": true,
                    "destOverride": [
                        "http",
                        "tls"
                    ],
                    "routeOnly": false
                },
                "settings": {
                    "auth": "noauth",
                    "udp": true,
                    "allowTransparent": false
                }
            }
        ],
        "remarks": "Austria: || Aeza International LTD"
    },
    {
        "log": {
            "access": "",
            "error": "",
            "loglevel": "warning"
        },
        "outbounds": [
            {
                "tag": "proxy",
                "protocol": "vless",
                "settings": {
                    "vnext": [
                        {
                            "address": "\n<html><head>\n<meta http-equiv=\"content-type\" content=\"text/html;charset=utf-8\">\n<title>403 Forbidden</title>\n</head>\n<body text=#000000 bgcolor=#ffffff>\n<h1>Error: Forbidden</h1>\n<h2>Your client does not have permission to get URL <code>/api/</code> from this server.</h2>\n<h2></h2>\n</body></html>\n",
                            "port": 15000,
                            "users": [
                                {
                                    "id": "38c78d80-38b8-4692-914a-f7cb6356a0e1",
                                    "alterId": 0,
                                    "email": "t@t.tt",
                                    "security": "auto",
                                    "encryption": "none",
                                    "flow": ""
                                }
                            ]
                        }
                    ]
                },
                "streamSettings": {
                    "network": "tcp",
                    "tcpSettings": {
                        "header": {
                            "type": "http",
                            "request": {
                                "version": "1.1",
                                "method": "GET",
                                "path": [
                                    "/"
                                ],
                                "headers": {
                                    "Host": [
                                        "rubika.ir.igap.net.soft98.ir"
                                    ],
                                    "User-Agent": [
                                        ""
                                    ],
                                    "Accept-Encoding": [
                                        "gzip, deflate"
                                    ],
                                    "Connection": [
                                        "keep-alive"
                                    ],
                                    "Pragma": "no-cache"
                                }
                            }
                        }
                    }
                },
                "mux": {
                    "enabled": false,
                    "concurrency": -1
                }
            },
            {
                "tag": "direct",
                "protocol": "freedom",
                "settings": {}
            },
            {
                "tag": "block",
                "protocol": "blackhole",
                "settings": {
                    "response": {
                        "type": "http"
                    }
                }
            }
        ],
        "inbounds": [
            {
                "tag": "socks",
                "port": 10808,
                "listen": "127.0.0.1",
                "protocol": "socks",
                "sniffing": {
                    "enabled": true,
                    "destOverride": [
                        "http",
                        "tls"
                    ],
                    "routeOnly": false
                },
                "settings": {
                    "auth": "noauth",
                    "udp": true,
                    "allowTransparent": false
                }
            },
            {
                "tag": "http",
                "port": 10809,
                "listen": "127.0.0.1",
                "protocol": "http",
                "sniffing": {
                    "enabled": true,
                    "destOverride": [
                        "http",
                        "tls"
                    ],
                    "routeOnly": false
                },
                "settings": {
                    "auth": "noauth",
                    "udp": true,
                    "allowTransparent": false
                }
            }
        ],
        "remarks": "Spain: || BlueVPS OU"
    },
    {
        "log": {
            "access": "",
            "error": "",
            "loglevel": "warning"
        },
        "outbounds": [
            {
                "tag": "proxy",
                "protocol": "vless",
                "settings": {
                    "vnext": [
                        {
                            "address": "\n<html><head>\n<meta http-equiv=\"content-type\" content=\"text/html;charset=utf-8\">\n<title>403 Forbidden</title>\n</head>\n<body text=#000000 bgcolor=#ffffff>\n<h1>Error: Forbidden</h1>\n<h2>Your client does not have permission to get URL <code>/api/</code> from this server.</h2>\n<h2></h2>\n</body></html>\n",
                            "port": 2089,
                            "users": [
                                {
                                    "id": "c95740bb-b3be-44f9-9fa4-260c3fbec6de",
                                    "alterId": 0,
                                    "email": "t@t.tt",
                                    "security": "auto",
                                    "encryption": "none",
                                    "flow": ""
                                }
                            ]
                        }
                    ]
                },
                "streamSettings": {
                    "network": "tcp",
                    "security": "reality",
                    "realitySettings": {
                        "serverName": "refersion.com",
                        "fingerprint": "chrome",
                        "show": false,
                        "publicKey": "bvEBes1y2n6327dEgJyZTR6Xz_EuyfLdkEX7DxWGFFg",
                        "shortId": "e3c5c005cae07eb8",
                        "spiderX": ""
                    }
                },
                "mux": {
                    "enabled": false,
                    "concurrency": -1
                }
            },
            {
                "tag": "direct",
                "protocol": "freedom",
                "settings": {}
            },
            {
                "tag": "block",
                "protocol": "blackhole",
                "settings": {
                    "response": {
                        "type": "http"
                    }
                }
            }
        ],
        "inbounds": [
            {
                "tag": "socks",
                "port": 10808,
                "listen": "127.0.0.1",
                "protocol": "socks",
                "sniffing": {
                    "enabled": true,
                    "destOverride": [
                        "http",
                        "tls"
                    ],
                    "routeOnly": false
                },
                "settings": {
                    "auth": "noauth",
                    "udp": true,
                    "allowTransparent": false
                }
            },
            {
                "tag": "http",
                "port": 10809,
                "listen": "127.0.0.1",
                "protocol": "http",
                "sniffing": {
                    "enabled": true,
                    "destOverride": [
                        "http",
                        "tls"
                    ],
                    "routeOnly": false
                },
                "settings": {
                    "auth": "noauth",
                    "udp": true,
                    "allowTransparent": false
                }
            }
        ],
        "remarks": "Germany: || Hetzner Online GmbH"
    },
    {
        "log": {
            "access": "",
            "error": "",
            "loglevel": "warning"
        },
        "outbounds": [
            {
                "tag": "proxy",
                "protocol": "vless",
                "settings": {
                    "vnext": [
                        {
                            "address": "2607:5300:205:200::5751",
                            "port": 443,
                            "users": [
                                {
                                    "id": "ccfd04dc-202e-4e11-aafe-a133dc8f7645",
                                    "alterId": 0,
                                    "email": "t@t.tt",
                                    "security": "auto",
                                    "encryption": "none",
                                    "flow": ""
                                }
                            ]
                        }
                    ]
                },
                "streamSettings": {
                    "network": "grpc",
                    "grpcSettings": {
                        "serviceName": "",
                        "multiMode": false,
                        "idle_timeout": 60,
                        "health_check_timeout": 20,
                        "permit_without_stream": false,
                        "initial_windows_size": 0
                    }
                },
                "mux": {
                    "enabled": false,
                    "concurrency": -1
                }
            },
            {
                "tag": "direct",
                "protocol": "freedom",
                "settings": {}
            },
            {
                "tag": "block",
                "protocol": "blackhole",
                "settings": {
                    "response": {
                        "type": "http"
                    }
                }
            }
        ],
        "inbounds": [
            {
                "tag": "socks",
                "port": 10808,
                "listen": "127.0.0.1",
                "protocol": "socks",
                "sniffing": {
                    "enabled": true,
                    "destOverride": [
                        "http",
                        "tls"
                    ],
                    "routeOnly": false
                },
                "settings": {
                    "auth": "noauth",
                    "udp": true,
                    "allowTransparent": false
                }
            },
            {
                "tag": "http",
                "port": 10809,
                "listen": "127.0.0.1",
                "protocol": "http",
                "sniffing": {
                    "enabled": true,
                    "destOverride": [
                        "http",
                        "tls"
                    ],
                    "routeOnly": false
                },
                "settings": {
                    "auth": "noauth",
                    "udp": true,
                    "allowTransparent": false
                }
            }
        ],
        "remarks": "Canada: || OVH SAS"
    },
    {
        "log": {
            "access": "",
            "error": "",
            "loglevel": "warning"
        },
        "outbounds": [
            {
                "tag": "proxy",
                "protocol": "vless",
                "settings": {
                    "vnext": [
                        {
                            "address": "2603:c024:c012:2a23::1121",
                            "port": 2087,
                            "users": [
                                {
                                    "id": "bf86d7a4-30fe-44fd-bb12-15ce3924ad40",
                                    "alterId": 0,
                                    "email": "t@t.tt",
                                    "security": "auto",
                                    "encryption": "none",
                                    "flow": "xtls-rprx-vision"
                                }
                            ]
                        }
                    ]
                },
                "streamSettings": {
                    "network": "tcp",
                    "security": "reality",
                    "realitySettings": {
                        "serverName": "www.yahoo.com",
                        "fingerprint": "chrome",
                        "show": false,
                        "publicKey": "LukOig0eMe6VNy9rdyFt7ozZpS3r_1lsyIMun4qgJEo",
                        "shortId": "d27cd3b5",
                        "spiderX": ""
                    }
                },
                "mux": {
                    "enabled": false,
                    "concurrency": -1
                }
            },
            {
                "tag": "direct",
                "protocol": "freedom",
                "settings": {}
            },
            {
                "tag": "block",
                "protocol": "blackhole",
                "settings": {
                    "response": {
                        "type": "http"
                    }
                }
            }
        ],
        "inbounds": [
            {
                "tag": "socks",
                "port": 10808,
                "listen": "127.0.0.1",
                "protocol": "socks",
                "sniffing": {
                    "enabled": true,
                    "destOverride": [
                        "http",
                        "tls"
                    ],
                    "routeOnly": false
                },
                "settings": {
                    "auth": "noauth",
                    "udp": true,
                    "allowTransparent": false
                }
            },
            {
                "tag": "http",
                "port": 10809,
                "listen": "127.0.0.1",
                "protocol": "http",
                "sniffing": {
                    "enabled": true,
                    "destOverride": [
                        "http",
                        "tls"
                    ],
                    "routeOnly": false
                },
                "settings": {
                    "auth": "noauth",
                    "udp": true,
                    "allowTransparent": false
                }
            }
        ],
        "remarks": "United States: || Oracle Corporation"
    },
    {
        "log": {
            "access": "",
            "error": "",
            "loglevel": "warning"
        },
        "outbounds": [
            {
                "tag": "proxy",
                "protocol": "vless",
                "settings": {
                    "vnext": [
                        {
                            "address": "2a01:4f8:c2c:8f30::1",
                            "port": 31904,
                            "users": [
                                {
                                    "id": "37e9ed0b-bde6-48ad-b837-9f19a5bbc80f",
                                    "alterId": 0,
                                    "email": "t@t.tt",
                                    "security": "auto",
                                    "encryption": "none",
                                    "flow": ""
                                }
                            ]
                        }
                    ]
                },
                "streamSettings": {
                    "network": "tcp"
                },
                "mux": {
                    "enabled": false,
                    "concurrency": -1
                }
            },
            {
                "tag": "direct",
                "protocol": "freedom",
                "settings": {}
            },
            {
                "tag": "block",
                "protocol": "blackhole",
                "settings": {
                    "response": {
                        "type": "http"
                    }
                }
            }
        ],
        "inbounds": [
            {
                "tag": "socks",
                "port": 10808,
                "listen": "127.0.0.1",
                "protocol": "socks",
                "sniffing": {
                    "enabled": true,
                    "destOverride": [
                        "http",
                        "tls"
                    ],
                    "routeOnly": false
                },
                "settings": {
                    "auth": "noauth",
                    "udp": true,
                    "allowTransparent": false
                }
            },
            {
                "tag": "http",
                "port": 10809,
                "listen": "127.0.0.1",
                "protocol": "http",
                "sniffing": {
                    "enabled": true,
                    "destOverride": [
                        "http",
                        "tls"
                    ],
                    "routeOnly": false
                },
                "settings": {
                    "auth": "noauth",
                    "udp": true,
                    "allowTransparent": false
                }
            }
        ],
        "remarks": "Germany: || Hetzner Online GmbH"
    },
    {
        "log": {
            "access": "",
            "error": "",
            "loglevel": "warning"
        },
        "outbounds": [
            {
                "tag": "proxy",
                "protocol": "vless",
                "settings": {
                    "vnext": [
                        {
                            "address": "\n<html><head>\n<meta http-equiv=\"content-type\" content=\"text/html;charset=utf-8\">\n<title>403 Forbidden</title>\n</head>\n<body text=#000000 bgcolor=#ffffff>\n<h1>Error: Forbidden</h1>\n<h2>Your client does not have permission to get URL <code>/api/</code> from this server.</h2>\n<h2></h2>\n</body></html>\n",
                            "port": 14000,
                            "users": [
                                {
                                    "id": "51b73782-3536-48d7-b125-9e3f48c4052f",
                                    "alterId": 0,
                                    "email": "t@t.tt",
                                    "security": "auto",
                                    "encryption": "none",
                                    "flow": ""
                                }
                            ]
                        }
                    ]
                },
                "streamSettings": {
                    "network": "tcp",
                    "tcpSettings": {
                        "header": {
                            "type": "http",
                            "request": {
                                "version": "1.1",
                                "method": "GET",
                                "path": [
                                    "/"
                                ],
                                "headers": {
                                    "Host": [
                                        "rubika.ir.igap.net.soft98.ir"
                                    ],
                                    "User-Agent": [
                                        ""
                                    ],
                                    "Accept-Encoding": [
                                        "gzip, deflate"
                                    ],
                                    "Connection": [
                                        "keep-alive"
                                    ],
                                    "Pragma": "no-cache"
                                }
                            }
                        }
                    }
                },
                "mux": {
                    "enabled": false,
                    "concurrency": -1
                }
            },
            {
                "tag": "direct",
                "protocol": "freedom",
                "settings": {}
            },
            {
                "tag": "block",
                "protocol": "blackhole",
                "settings": {
                    "response": {
                        "type": "http"
                    }
                }
            }
        ],
        "inbounds": [
            {
                "tag": "socks",
                "port": 10808,
                "listen": "127.0.0.1",
                "protocol": "socks",
                "sniffing": {
                    "enabled": true,
                    "destOverride": [
                        "http",
                        "tls"
                    ],
                    "routeOnly": false
                },
                "settings": {
                    "auth": "noauth",
                    "udp": true,
                    "allowTransparent": false
                }
            },
            {
                "tag": "http",
                "port": 10809,
                "listen": "127.0.0.1",
                "protocol": "http",
                "sniffing": {
                    "enabled": true,
                    "destOverride": [
                        "http",
                        "tls"
                    ],
                    "routeOnly": false
                },
                "settings": {
                    "auth": "noauth",
                    "udp": true,
                    "allowTransparent": false
                }
            }
        ],
        "remarks": "France: || OVH SAS"
    },
    {
        "log": {
            "access": "",
            "error": "",
            "loglevel": "warning"
        },
        "outbounds": [
            {
                "tag": "proxy",
                "protocol": "vless",
                "settings": {
                    "vnext": [
                        {
                            "address": "\n<html><head>\n<meta http-equiv=\"content-type\" content=\"text/html;charset=utf-8\">\n<title>403 Forbidden</title>\n</head>\n<body text=#000000 bgcolor=#ffffff>\n<h1>Error: Forbidden</h1>\n<h2>Your client does not have permission to get URL <code>/api/</code> from this server.</h2>\n<h2></h2>\n</body></html>\n",
                            "port": 443,
                            "users": [
                                {
                                    "id": "440766d1-858f-4719-84f5-c2de6f6227ba",
                                    "alterId": 0,
                                    "email": "t@t.tt",
                                    "security": "auto",
                                    "encryption": "none",
                                    "flow": ""
                                }
                            ]
                        }
                    ]
                },
                "streamSettings": {
                    "network": "tcp",
                    "security": "tls",
                    "tlsSettings": {
                        "allowInsecure": true,
                        "serverName": "local.rogsoftwaregroup.com",
                        "alpn": [
                            "http/1.1",
                            "h2",
                            "h3"
                        ],
                        "show": false
                    }
                },
                "mux": {
                    "enabled": false,
                    "concurrency": -1
                }
            },
            {
                "tag": "direct",
                "protocol": "freedom",
                "settings": {}
            },
            {
                "tag": "block",
                "protocol": "blackhole",
                "settings": {
                    "response": {
                        "type": "http"
                    }
                }
            }
        ],
        "inbounds": [
            {
                "tag": "socks",
                "port": 10808,
                "listen": "127.0.0.1",
                "protocol": "socks",
                "sniffing": {
                    "enabled": true,
                    "destOverride": [
                        "http",
                        "tls"
                    ],
                    "routeOnly": false
                },
                "settings": {
                    "auth": "noauth",
                    "udp": true,
                    "allowTransparent": false
                }
            },
            {
                "tag": "http",
                "port": 10809,
                "listen": "127.0.0.1",
                "protocol": "http",
                "sniffing": {
                    "enabled": true,
                    "destOverride": [
                        "http",
                        "tls"
                    ],
                    "routeOnly": false
                },
                "settings": {
                    "auth": "noauth",
                    "udp": true,
                    "allowTransparent": false
                }
            }
        ],
        "remarks": "Finland: || Hetzner Online GmbH"
    },
    {
        "log": {
            "access": "",
            "error": "",
            "loglevel": "warning"
        },
        "outbounds": [
            {
                "tag": "proxy",
                "protocol": "vless",
                "settings": {
                    "vnext": [
                        {
                            "address": "2a00:1838:37:336::e593",
                            "port": 19000,
                            "users": [
                                {
                                    "id": "e11d11cc-e6bb-4a00-b9f9-279ef71360d4",
                                    "alterId": 0,
                                    "email": "t@t.tt",
                                    "security": "auto",
                                    "encryption": "none",
                                    "flow": ""
                                }
                            ]
                        }
                    ]
                },
                "streamSettings": {
                    "network": "tcp",
                    "tcpSettings": {
                        "header": {
                            "type": "http",
                            "request": {
                                "version": "1.1",
                                "method": "GET",
                                "path": [
                                    "/"
                                ],
                                "headers": {
                                    "Host": [
                                        "rubika.ir.igap.net.soft98.ir"
                                    ],
                                    "User-Agent": [
                                        ""
                                    ],
                                    "Accept-Encoding": [
                                        "gzip, deflate"
                                    ],
                                    "Connection": [
                                        "keep-alive"
                                    ],
                                    "Pragma": "no-cache"
                                }
                            }
                        }
                    }
                },
                "mux": {
                    "enabled": false,
                    "concurrency": -1
                }
            },
            {
                "tag": "direct",
                "protocol": "freedom",
                "settings": {}
            },
            {
                "tag": "block",
                "protocol": "blackhole",
                "settings": {
                    "response": {
                        "type": "http"
                    }
                }
            }
        ],
        "inbounds": [
            {
                "tag": "socks",
                "port": 10808,
                "listen": "127.0.0.1",
                "protocol": "socks",
                "sniffing": {
                    "enabled": true,
                    "destOverride": [
                        "http",
                        "tls"
                    ],
                    "routeOnly": false
                },
                "settings": {
                    "auth": "noauth",
                    "udp": true,
                    "allowTransparent": false
                }
            },
            {
                "tag": "http",
                "port": 10809,
                "listen": "127.0.0.1",
                "protocol": "http",
                "sniffing": {
                    "enabled": true,
                    "destOverride": [
                        "http",
                        "tls"
                    ],
                    "routeOnly": false
                },
                "settings": {
                    "auth": "noauth",
                    "udp": true,
                    "allowTransparent": false
                }
            }
        ],
        "remarks": "Russia: || Veesp datacenter"
    },
    {
        "log": {
            "access": "",
            "error": "",
            "loglevel": "warning"
        },
        "outbounds": [
            {
                "tag": "proxy",
                "protocol": "vless",
                "settings": {
                    "vnext": [
                        {
                            "address": "2604:2dc0:101:100::103c",
                            "port": 443,
                            "users": [
                                {
                                    "id": "84630ddd-b04a-4494-aa3a-b831a9873b81",
                                    "alterId": 0,
                                    "email": "t@t.tt",
                                    "security": "auto",
                                    "encryption": "none",
                                    "flow": ""
                                }
                            ]
                        }
                    ]
                },
                "streamSettings": {
                    "network": "ws",
                    "wsSettings": {
                        "path": "/linkws?ed",
                        "headers": {
                            "Host": "maxnetvipaP-us4.NetKh3.sItE"
                        }
                    },
                    "security": "tls",
                    "tlsSettings": {
                        "allowInsecure": true,
                        "serverName": "maxnetvipaP-us4.NetKh3.sItE",
                        "alpn": []
                    }
                },
                "mux": {
                    "enabled": false,
                    "concurrency": -1
                }
            },
            {
                "tag": "direct",
                "protocol": "freedom",
                "settings": {}
            },
            {
                "tag": "block",
                "protocol": "blackhole",
                "settings": {
                    "response": {
                        "type": "http"
                    }
                }
            }
        ],
        "inbounds": [
            {
                "tag": "socks",
                "port": 10808,
                "listen": "127.0.0.1",
                "protocol": "socks",
                "sniffing": {
                    "enabled": true,
                    "destOverride": [
                        "http",
                        "tls"
                    ],
                    "routeOnly": false
                },
                "settings": {
                    "auth": "noauth",
                    "udp": true,
                    "allowTransparent": false
                }
            },
            {
                "tag": "http",
                "port": 10809,
                "listen": "127.0.0.1",
                "protocol": "http",
                "sniffing": {
                    "enabled": true,
                    "destOverride": [
                        "http",
                        "tls"
                    ],
                    "routeOnly": false
                },
                "settings": {
                    "auth": "noauth",
                    "udp": true,
                    "allowTransparent": false
                }
            }
        ],
        "remarks": "United States: || OVH SAS"
    },
    {
        "log": {
            "access": "",
            "error": "",
            "loglevel": "warning"
        },
        "outbounds": [
            {
                "tag": "proxy",
                "protocol": "vless",
                "settings": {
                    "vnext": [
                        {
                            "address": "\n<html><head>\n<meta http-equiv=\"content-type\" content=\"text/html;charset=utf-8\">\n<title>403 Forbidden</title>\n</head>\n<body text=#000000 bgcolor=#ffffff>\n<h1>Error: Forbidden</h1>\n<h2>Your client does not have permission to get URL <code>/api/</code> from this server.</h2>\n<h2></h2>\n</body></html>\n",
                            "port": 8080,
                            "users": [
                                {
                                    "id": "telegram-id-ArV2ray",
                                    "alterId": 0,
                                    "email": "t@t.tt",
                                    "security": "auto",
                                    "encryption": "none",
                                    "flow": ""
                                }
                            ]
                        }
                    ]
                },
                "streamSettings": {
                    "network": "ws",
                    "wsSettings": {
                        "path": "/telegram-ArV2ry,telegram-ArV2ry,telegram-ArV2ry,telegram-ArV2ry,telegram-ArV2ry,telegram-ArV2ry,telegram-ArV2ry,telegram-ArV2ry,telegram-ArV2ry,telegram-ArV2ry?ed=2048",
                        "headers": {
                            "Host": "Www.speedtest.net.irna.ir.www.webdade.com.2.ipsq.ddns-ip.net."
                        }
                    }
                },
                "mux": {
                    "enabled": false,
                    "concurrency": -1
                }
            },
            {
                "tag": "direct",
                "protocol": "freedom",
                "settings": {}
            },
            {
                "tag": "block",
                "protocol": "blackhole",
                "settings": {
                    "response": {
                        "type": "http"
                    }
                }
            }
        ],
        "inbounds": [
            {
                "tag": "socks",
                "port": 10808,
                "listen": "127.0.0.1",
                "protocol": "socks",
                "sniffing": {
                    "enabled": true,
                    "destOverride": [
                        "http",
                        "tls"
                    ],
                    "routeOnly": false
                },
                "settings": {
                    "auth": "noauth",
                    "udp": true,
                    "allowTransparent": false
                }
            },
            {
                "tag": "http",
                "port": 10809,
                "listen": "127.0.0.1",
                "protocol": "http",
                "sniffing": {
                    "enabled": true,
                    "destOverride": [
                        "http",
                        "tls"
                    ],
                    "routeOnly": false
                },
                "settings": {
                    "auth": "noauth",
                    "udp": true,
                    "allowTransparent": false
                }
            }
        ],
        "remarks": "United Kingdom: || Zhejiang Aiyun Network Technology Co Ltd"
    },
    {
        "log": {
            "access": "",
            "error": "",
            "loglevel": "warning"
        },
        "outbounds": [
            {
                "tag": "proxy",
                "protocol": "vless",
                "settings": {
                    "vnext": [
                        {
                            "address": "\n<html><head>\n<meta http-equiv=\"content-type\" content=\"text/html;charset=utf-8\">\n<title>403 Forbidden</title>\n</head>\n<body text=#000000 bgcolor=#ffffff>\n<h1>Error: Forbidden</h1>\n<h2>Your client does not have permission to get URL <code>/api/</code> from this server.</h2>\n<h2></h2>\n</body></html>\n",
                            "port": 80,
                            "users": [
                                {
                                    "id": "telegram-ArV2ray",
                                    "alterId": 0,
                                    "email": "t@t.tt",
                                    "security": "auto",
                                    "encryption": "none",
                                    "flow": ""
                                }
                            ]
                        }
                    ]
                },
                "streamSettings": {
                    "network": "ws",
                    "wsSettings": {
                        "path": "/telegram-ArV2ry,telegram-ArV2ry,telegram-ArV2ry,telegram-ArV2ry,telegram-ArV2ry,telegram-ArV2ry,telegram-ArV2ry,telegram-ArV2ry,telegram-ArV2ry,telegram-ArV2ry,telegram-ArV2ry",
                        "headers": {
                            "Host": "www.speedtest.net.ab.2.mehpow.ir."
                        }
                    }
                },
                "mux": {
                    "enabled": false,
                    "concurrency": -1
                }
            },
            {
                "tag": "direct",
                "protocol": "freedom",
                "settings": {}
            },
            {
                "tag": "block",
                "protocol": "blackhole",
                "settings": {
                    "response": {
                        "type": "http"
                    }
                }
            }
        ],
        "inbounds": [
            {
                "tag": "socks",
                "port": 10808,
                "listen": "127.0.0.1",
                "protocol": "socks",
                "sniffing": {
                    "enabled": true,
                    "destOverride": [
                        "http",
                        "tls"
                    ],
                    "routeOnly": false
                },
                "settings": {
                    "auth": "noauth",
                    "udp": true,
                    "allowTransparent": false
                }
            },
            {
                "tag": "http",
                "port": 10809,
                "listen": "127.0.0.1",
                "protocol": "http",
                "sniffing": {
                    "enabled": true,
                    "destOverride": [
                        "http",
                        "tls"
                    ],
                    "routeOnly": false
                },
                "settings": {
                    "auth": "noauth",
                    "udp": true,
                    "allowTransparent": false
                }
            }
        ],
        "remarks": "United Kingdom: || Zhejiang Aiyun Network Technology Co Ltd"
    },
    {
        "log": {
            "access": "",
            "error": "",
            "loglevel": "warning"
        },
        "outbounds": [
            {
                "tag": "proxy",
                "protocol": "vless",
                "settings": {
                    "vnext": [
                        {
                            "address": "\n<html><head>\n<meta http-equiv=\"content-type\" content=\"text/html;charset=utf-8\">\n<title>403 Forbidden</title>\n</head>\n<body text=#000000 bgcolor=#ffffff>\n<h1>Error: Forbidden</h1>\n<h2>Your client does not have permission to get URL <code>/api/</code> from this server.</h2>\n<h2></h2>\n</body></html>\n",
                            "port": 8880,
                            "users": [
                                {
                                    "id": "Parsashonam-220",
                                    "alterId": 0,
                                    "email": "t@t.tt",
                                    "security": "auto",
                                    "encryption": "none",
                                    "flow": ""
                                }
                            ]
                        }
                    ]
                },
                "streamSettings": {
                    "network": "httpupgrade",
                    "httpupgradeSettings": {
                        "path": "/",
                        "host": "Search.DigiKala.CYoU."
                    }
                },
                "mux": {
                    "enabled": false,
                    "concurrency": -1
                }
            },
            {
                "tag": "direct",
                "protocol": "freedom",
                "settings": {}
            },
            {
                "tag": "block",
                "protocol": "blackhole",
                "settings": {
                    "response": {
                        "type": "http"
                    }
                }
            }
        ],
        "inbounds": [
            {
                "tag": "socks",
                "port": 10808,
                "listen": "127.0.0.1",
                "protocol": "socks",
                "sniffing": {
                    "enabled": true,
                    "destOverride": [
                        "http",
                        "tls"
                    ],
                    "routeOnly": false
                },
                "settings": {
                    "auth": "noauth",
                    "udp": true,
                    "allowTransparent": false
                }
            },
            {
                "tag": "http",
                "port": 10809,
                "listen": "127.0.0.1",
                "protocol": "http",
                "sniffing": {
                    "enabled": true,
                    "destOverride": [
                        "http",
                        "tls"
                    ],
                    "routeOnly": false
                },
                "settings": {
                    "auth": "noauth",
                    "udp": true,
                    "allowTransparent": false
                }
            }
        ],
        "remarks": "Germany: || Hetzner Online GmbH"
    },
    {
        "log": {
            "access": "",
            "error": "",
            "loglevel": "warning"
        },
        "outbounds": [
            {
                "tag": "proxy",
                "protocol": "vless",
                "settings": {
                    "vnext": [
                        {
                            "address": "\n<html><head>\n<meta http-equiv=\"content-type\" content=\"text/html;charset=utf-8\">\n<title>403 Forbidden</title>\n</head>\n<body text=#000000 bgcolor=#ffffff>\n<h1>Error: Forbidden</h1>\n<h2>Your client does not have permission to get URL <code>/api/</code> from this server.</h2>\n<h2></h2>\n</body></html>\n",
                            "port": 80,
                            "users": [
                                {
                                    "id": "Parsashonam-220",
                                    "alterId": 0,
                                    "email": "t@t.tt",
                                    "security": "auto",
                                    "encryption": "none",
                                    "flow": ""
                                }
                            ]
                        }
                    ]
                },
                "streamSettings": {
                    "network": "ws",
                    "wsSettings": {
                        "path": "/@Parsashonam?ed=2048",
                        "headers": {
                            "Host": "Parsashonam-DE.ir"
                        }
                    }
                },
                "mux": {
                    "enabled": false,
                    "concurrency": -1
                }
            },
            {
                "tag": "direct",
                "protocol": "freedom",
                "settings": {}
            },
            {
                "tag": "block",
                "protocol": "blackhole",
                "settings": {
                    "response": {
                        "type": "http"
                    }
                }
            }
        ],
        "inbounds": [
            {
                "tag": "socks",
                "port": 10808,
                "listen": "127.0.0.1",
                "protocol": "socks",
                "sniffing": {
                    "enabled": true,
                    "destOverride": [
                        "http",
                        "tls"
                    ],
                    "routeOnly": false
                },
                "settings": {
                    "auth": "noauth",
                    "udp": true,
                    "allowTransparent": false
                }
            },
            {
                "tag": "http",
                "port": 10809,
                "listen": "127.0.0.1",
                "protocol": "http",
                "sniffing": {
                    "enabled": true,
                    "destOverride": [
                        "http",
                        "tls"
                    ],
                    "routeOnly": false
                },
                "settings": {
                    "auth": "noauth",
                    "udp": true,
                    "allowTransparent": false
                }
            }
        ],
        "remarks": "Germany: || Hetzner Online GmbH"
    },
    {
        "log": {
            "access": "",
            "error": "",
            "loglevel": "warning"
        },
        "outbounds": [
            {
                "tag": "proxy",
                "protocol": "vless",
                "settings": {
                    "vnext": [
                        {
                            "address": "\n<html><head>\n<meta http-equiv=\"content-type\" content=\"text/html;charset=utf-8\">\n<title>403 Forbidden</title>\n</head>\n<body text=#000000 bgcolor=#ffffff>\n<h1>Error: Forbidden</h1>\n<h2>Your client does not have permission to get URL <code>/api/</code> from this server.</h2>\n<h2></h2>\n</body></html>\n",
                            "port": 80,
                            "users": [
                                {
                                    "id": "1554b16a-61d8-4efc-864a-bf18790e926c",
                                    "alterId": 0,
                                    "email": "t@t.tt",
                                    "security": "auto",
                                    "encryption": "none",
                                    "flow": ""
                                }
                            ]
                        }
                    ]
                },
                "streamSettings": {
                    "network": "ws",
                    "wsSettings": {
                        "path": "/@Shh_Proxy----@Shh_Proxy----@Shh_Proxy----@Shh_Proxy----@Shh_Proxy----@Shh_Proxy----@Shh_Proxy----@Shh_Proxy----@Shh_Proxy----@Shh_Proxy----@Shh_Proxy----@Shh_Proxy?ed=2048",
                        "headers": {
                            "Host": "Www.speedtest.net.speedtest2.cfd."
                        }
                    }
                },
                "mux": {
                    "enabled": false,
                    "concurrency": -1
                }
            },
            {
                "tag": "direct",
                "protocol": "freedom",
                "settings": {}
            },
            {
                "tag": "block",
                "protocol": "blackhole",
                "settings": {
                    "response": {
                        "type": "http"
                    }
                }
            }
        ],
        "inbounds": [
            {
                "tag": "socks",
                "port": 10808,
                "listen": "127.0.0.1",
                "protocol": "socks",
                "sniffing": {
                    "enabled": true,
                    "destOverride": [
                        "http",
                        "tls"
                    ],
                    "routeOnly": false
                },
                "settings": {
                    "auth": "noauth",
                    "udp": true,
                    "allowTransparent": false
                }
            },
            {
                "tag": "http",
                "port": 10809,
                "listen": "127.0.0.1",
                "protocol": "http",
                "sniffing": {
                    "enabled": true,
                    "destOverride": [
                        "http",
                        "tls"
                    ],
                    "routeOnly": false
                },
                "settings": {
                    "auth": "noauth",
                    "udp": true,
                    "allowTransparent": false
                }
            }
        ],
        "remarks": "Germany: || Hetzner Online GmbH"
    },
    {
        "log": {
            "access": "",
            "error": "",
            "loglevel": "warning"
        },
        "outbounds": [
            {
                "tag": "proxy",
                "protocol": "vless",
                "settings": {
                    "vnext": [
                        {
                            "address": "2001:41d0:701:1000::4630",
                            "port": 26528,
                            "users": [
                                {
                                    "id": "422e7615-23b0-4d42-83ad-25e9a7e6d295",
                                    "alterId": 0,
                                    "email": "t@t.tt",
                                    "security": "auto",
                                    "encryption": "none",
                                    "flow": ""
                                }
                            ]
                        }
                    ]
                },
                "streamSettings": {
                    "network": "grpc",
                    "security": "reality",
                    "realitySettings": {
                        "serverName": "yahoo.com",
                        "fingerprint": "chrome",
                        "show": false,
                        "publicKey": "2FrbyUtv6Ajh0Ufmst5Tw0ch_aeF3tXw0kDcfOrvGTk",
                        "shortId": "8f9d4d9a",
                        "spiderX": ""
                    },
                    "grpcSettings": {
                        "serviceName": "",
                        "multiMode": false,
                        "idle_timeout": 60,
                        "health_check_timeout": 20,
                        "permit_without_stream": false,
                        "initial_windows_size": 0
                    }
                },
                "mux": {
                    "enabled": false,
                    "concurrency": -1
                }
            },
            {
                "tag": "direct",
                "protocol": "freedom",
                "settings": {}
            },
            {
                "tag": "block",
                "protocol": "blackhole",
                "settings": {
                    "response": {
                        "type": "http"
                    }
                }
            }
        ],
        "inbounds": [
            {
                "tag": "socks",
                "port": 10808,
                "listen": "127.0.0.1",
                "protocol": "socks",
                "sniffing": {
                    "enabled": true,
                    "destOverride": [
                        "http",
                        "tls"
                    ],
                    "routeOnly": false
                },
                "settings": {
                    "auth": "noauth",
                    "udp": true,
                    "allowTransparent": false
                }
            },
            {
                "tag": "http",
                "port": 10809,
                "listen": "127.0.0.1",
                "protocol": "http",
                "sniffing": {
                    "enabled": true,
                    "destOverride": [
                        "http",
                        "tls"
                    ],
                    "routeOnly": false
                },
                "settings": {
                    "auth": "noauth",
                    "udp": true,
                    "allowTransparent": false
                }
            }
        ],
        "remarks": "United Kingdom: || OVH SAS"
    },
    {
        "log": {
            "access": "",
            "error": "",
            "loglevel": "warning"
        },
        "outbounds": [
            {
                "tag": "proxy",
                "protocol": "vless",
                "settings": {
                    "vnext": [
                        {
                            "address": "2a01:4f8:1c1b:25b9::1",
                            "port": 80,
                            "users": [
                                {
                                    "id": "48108ffd-b20c-4d94-bf99-d3e3187a10c7",
                                    "alterId": 0,
                                    "email": "t@t.tt",
                                    "security": "auto",
                                    "encryption": "none",
                                    "flow": ""
                                }
                            ]
                        }
                    ]
                },
                "streamSettings": {
                    "network": "ws",
                    "wsSettings": {
                        "path": "/telegram-mitivpn-telegram-mitivpn-telegram-mitivpn?ed=2048",
                        "headers": {
                            "Host": "arzinja.info"
                        }
                    }
                },
                "mux": {
                    "enabled": false,
                    "concurrency": -1
                }
            },
            {
                "tag": "direct",
                "protocol": "freedom",
                "settings": {}
            },
            {
                "tag": "block",
                "protocol": "blackhole",
                "settings": {
                    "response": {
                        "type": "http"
                    }
                }
            }
        ],
        "inbounds": [
            {
                "tag": "socks",
                "port": 10808,
                "listen": "127.0.0.1",
                "protocol": "socks",
                "sniffing": {
                    "enabled": true,
                    "destOverride": [
                        "http",
                        "tls"
                    ],
                    "routeOnly": false
                },
                "settings": {
                    "auth": "noauth",
                    "udp": true,
                    "allowTransparent": false
                }
            },
            {
                "tag": "http",
                "port": 10809,
                "listen": "127.0.0.1",
                "protocol": "http",
                "sniffing": {
                    "enabled": true,
                    "destOverride": [
                        "http",
                        "tls"
                    ],
                    "routeOnly": false
                },
                "settings": {
                    "auth": "noauth",
                    "udp": true,
                    "allowTransparent": false
                }
            }
        ],
        "remarks": "Germany: || Hetzner Online GmbH"
    },
    {
        "log": {
            "access": "",
            "error": "",
            "loglevel": "warning"
        },
        "outbounds": [
            {
                "tag": "proxy",
                "protocol": "vless",
                "settings": {
                    "vnext": [
                        {
                            "address": "2001:41d0:701:1000::4630",
                            "port": 11045,
                            "users": [
                                {
                                    "id": "8ee70fca-e854-433d-b21e-f23ccc65833d",
                                    "alterId": 0,
                                    "email": "t@t.tt",
                                    "security": "auto",
                                    "encryption": "none",
                                    "flow": ""
                                }
                            ]
                        }
                    ]
                },
                "streamSettings": {
                    "network": "grpc",
                    "security": "reality",
                    "realitySettings": {
                        "serverName": "yahoo.com",
                        "fingerprint": "chrome",
                        "show": false,
                        "publicKey": "p-FNeH1T5de5nmwI7iT16MQKWspQ0b6C9GGSRwGtlnM",
                        "shortId": "20db1be5e1ab118a",
                        "spiderX": ""
                    },
                    "grpcSettings": {
                        "serviceName": "Tel : @NT_Safe",
                        "multiMode": false,
                        "idle_timeout": 60,
                        "health_check_timeout": 20,
                        "permit_without_stream": false,
                        "initial_windows_size": 0
                    }
                },
                "mux": {
                    "enabled": false,
                    "concurrency": -1
                }
            },
            {
                "tag": "direct",
                "protocol": "freedom",
                "settings": {}
            },
            {
                "tag": "block",
                "protocol": "blackhole",
                "settings": {
                    "response": {
                        "type": "http"
                    }
                }
            }
        ],
        "inbounds": [
            {
                "tag": "socks",
                "port": 10808,
                "listen": "127.0.0.1",
                "protocol": "socks",
                "sniffing": {
                    "enabled": true,
                    "destOverride": [
                        "http",
                        "tls"
                    ],
                    "routeOnly": false
                },
                "settings": {
                    "auth": "noauth",
                    "udp": true,
                    "allowTransparent": false
                }
            },
            {
                "tag": "http",
                "port": 10809,
                "listen": "127.0.0.1",
                "protocol": "http",
                "sniffing": {
                    "enabled": true,
                    "destOverride": [
                        "http",
                        "tls"
                    ],
                    "routeOnly": false
                },
                "settings": {
                    "auth": "noauth",
                    "udp": true,
                    "allowTransparent": false
                }
            }
        ],
        "remarks": "United Kingdom: || OVH SAS"
    },
    {
        "log": {
            "access": "",
            "error": "",
            "loglevel": "warning"
        },
        "outbounds": [
            {
                "tag": "proxy",
                "protocol": "vless",
                "settings": {
                    "vnext": [
                        {
                            "address": "2a01:4f8:1c1b:eee7::1",
                            "port": 2095,
                            "users": [
                                {
                                    "id": "cffb6269-efbc-4a99-a8b7-99af8fde79dd",
                                    "alterId": 0,
                                    "email": "t@t.tt",
                                    "security": "auto",
                                    "encryption": "none",
                                    "flow": ""
                                }
                            ]
                        }
                    ]
                },
                "streamSettings": {
                    "network": "ws",
                    "wsSettings": {
                        "path": "@XpnTeam----@XpnTeam----@XpnTeam----@XpnTeam----@XpnTeam----@XpnTeam----@XpnTeam----@XpnTeam----@XpnTeam----@XpnTeam----@XpnTeam----@XpnTeam----@XpnTeam----@XpnTeam----@XpnTeam----@XpnTeam?ed=2048flow=-udp443",
                        "headers": {
                            "Host": "xpntEamfree.sockSchangert.ir."
                        }
                    }
                },
                "mux": {
                    "enabled": false,
                    "concurrency": -1
                }
            },
            {
                "tag": "direct",
                "protocol": "freedom",
                "settings": {}
            },
            {
                "tag": "block",
                "protocol": "blackhole",
                "settings": {
                    "response": {
                        "type": "http"
                    }
                }
            }
        ],
        "inbounds": [
            {
                "tag": "socks",
                "port": 10808,
                "listen": "127.0.0.1",
                "protocol": "socks",
                "sniffing": {
                    "enabled": true,
                    "destOverride": [
                        "http",
                        "tls"
                    ],
                    "routeOnly": false
                },
                "settings": {
                    "auth": "noauth",
                    "udp": true,
                    "allowTransparent": false
                }
            },
            {
                "tag": "http",
                "port": 10809,
                "listen": "127.0.0.1",
                "protocol": "http",
                "sniffing": {
                    "enabled": true,
                    "destOverride": [
                        "http",
                        "tls"
                    ],
                    "routeOnly": false
                },
                "settings": {
                    "auth": "noauth",
                    "udp": true,
                    "allowTransparent": false
                }
            }
        ],
        "remarks": "Germany: || Hetzner Online GmbH"
    }
]