[
    {
        "log": {
            "access": "",
            "error": "",
            "loglevel": "warning"
        },
        "outbounds": [
            {
                "tag": "proxy",
                "protocol": "vless",
                "settings": {
                    "vnext": [
                        {
                            "address": "2a01:4f8:c010:71fc::1",
                            "port": 8080,
                            "users": [
                                {
                                    "id": "c87e429a-5ada-47b1-b4e5-d170648a1e6e",
                                    "alterId": 0,
                                    "email": "t@t.tt",
                                    "security": "auto",
                                    "encryption": "none",
                                    "flow": ""
                                }
                            ]
                        }
                    ]
                },
                "streamSettings": {
                    "network": "ws",
                    "wsSettings": {
                        "path": "/",
                        "headers": {
                            "Host": "h4.GraSsoRy.shop"
                        }
                    }
                },
                "mux": {
                    "enabled": false,
                    "concurrency": -1
                }
            },
            {
                "tag": "direct",
                "protocol": "freedom",
                "settings": {}
            },
            {
                "tag": "block",
                "protocol": "blackhole",
                "settings": {
                    "response": {
                        "type": "http"
                    }
                }
            }
        ],
        "inbounds": [
            {
                "tag": "socks",
                "port": 10808,
                "listen": "127.0.0.1",
                "protocol": "socks",
                "sniffing": {
                    "enabled": true,
                    "destOverride": [
                        "http",
                        "tls"
                    ],
                    "routeOnly": false
                },
                "settings": {
                    "auth": "noauth",
                    "udp": true,
                    "allowTransparent": false
                }
            },
            {
                "tag": "http",
                "port": 10809,
                "listen": "127.0.0.1",
                "protocol": "http",
                "sniffing": {
                    "enabled": true,
                    "destOverride": [
                        "http",
                        "tls"
                    ],
                    "routeOnly": false
                },
                "settings": {
                    "auth": "noauth",
                    "udp": true,
                    "allowTransparent": false
                }
            }
        ],
        "remarks": "Germany: || Hetzner Online AG"
    },
    {
        "log": {
            "access": "",
            "error": "",
            "loglevel": "warning"
        },
        "outbounds": [
            {
                "tag": "proxy",
                "protocol": "vless",
                "settings": {
                    "vnext": [
                        {
                            "address": "2604:a880:cad:d0::d733:9001",
                            "port": 80,
                            "users": [
                                {
                                    "id": "fcbbeaf6-b4c0-4fd0-b1db-2884994b5d48",
                                    "alterId": 0,
                                    "email": "t@t.tt",
                                    "security": "auto",
                                    "encryption": "none",
                                    "flow": ""
                                }
                            ]
                        }
                    ]
                },
                "streamSettings": {
                    "network": "tcp",
                    "tcpSettings": {
                        "header": {
                            "type": "http",
                            "request": {
                                "version": "1.1",
                                "method": "GET",
                                "path": [
                                    "/api/posts"
                                ],
                                "headers": {
                                    "Host": [
                                        "xs.90908585.ir"
                                    ],
                                    "User-Agent": [
                                        ""
                                    ],
                                    "Accept-Encoding": [
                                        "gzip, deflate"
                                    ],
                                    "Connection": [
                                        "keep-alive"
                                    ],
                                    "Pragma": "no-cache"
                                }
                            }
                        }
                    }
                },
                "mux": {
                    "enabled": false,
                    "concurrency": -1
                }
            },
            {
                "tag": "direct",
                "protocol": "freedom",
                "settings": {}
            },
            {
                "tag": "block",
                "protocol": "blackhole",
                "settings": {
                    "response": {
                        "type": "http"
                    }
                }
            }
        ],
        "inbounds": [
            {
                "tag": "socks",
                "port": 10808,
                "listen": "127.0.0.1",
                "protocol": "socks",
                "sniffing": {
                    "enabled": true,
                    "destOverride": [
                        "http",
                        "tls"
                    ],
                    "routeOnly": false
                },
                "settings": {
                    "auth": "noauth",
                    "udp": true,
                    "allowTransparent": false
                }
            },
            {
                "tag": "http",
                "port": 10809,
                "listen": "127.0.0.1",
                "protocol": "http",
                "sniffing": {
                    "enabled": true,
                    "destOverride": [
                        "http",
                        "tls"
                    ],
                    "routeOnly": false
                },
                "settings": {
                    "auth": "noauth",
                    "udp": true,
                    "allowTransparent": false
                }
            }
        ],
        "remarks": "Canada: || DigitalOcean, LLC"
    },
    {
        "log": {
            "access": "",
            "error": "",
            "loglevel": "warning"
        },
        "outbounds": [
            {
                "tag": "proxy",
                "protocol": "vless",
                "settings": {
                    "vnext": [
                        {
                            "address": "\n<html><head>\n<meta http-equiv=\"content-type\" content=\"text/html;charset=utf-8\">\n<title>403 Forbidden</title>\n</head>\n<body text=#000000 bgcolor=#ffffff>\n<h1>Error: Forbidden</h1>\n<h2>Your client does not have permission to get URL <code>/api/</code> from this server.</h2>\n<h2></h2>\n</body></html>\n",
                            "port": 2087,
                            "users": [
                                {
                                    "id": "5d71b518-9f52-414a-abf2-b806684233be",
                                    "alterId": 0,
                                    "email": "t@t.tt",
                                    "security": "auto",
                                    "encryption": "none",
                                    "flow": ""
                                }
                            ]
                        }
                    ]
                },
                "streamSettings": {
                    "network": "grpc",
                    "security": "tls",
                    "tlsSettings": {
                        "allowInsecure": true,
                        "serverName": "its.zarashop0.ir",
                        "alpn": [
                            "h2"
                        ],
                        "show": false,
                        "fingerprint": "chrome"
                    },
                    "grpcSettings": {
                        "serviceName": "",
                        "multiMode": false,
                        "idle_timeout": 60,
                        "health_check_timeout": 20,
                        "permit_without_stream": false,
                        "initial_windows_size": 0
                    }
                },
                "mux": {
                    "enabled": false,
                    "concurrency": -1
                }
            },
            {
                "tag": "direct",
                "protocol": "freedom",
                "settings": {}
            },
            {
                "tag": "block",
                "protocol": "blackhole",
                "settings": {
                    "response": {
                        "type": "http"
                    }
                }
            }
        ],
        "inbounds": [
            {
                "tag": "socks",
                "port": 10808,
                "listen": "127.0.0.1",
                "protocol": "socks",
                "sniffing": {
                    "enabled": true,
                    "destOverride": [
                        "http",
                        "tls"
                    ],
                    "routeOnly": false
                },
                "settings": {
                    "auth": "noauth",
                    "udp": true,
                    "allowTransparent": false
                }
            },
            {
                "tag": "http",
                "port": 10809,
                "listen": "127.0.0.1",
                "protocol": "http",
                "sniffing": {
                    "enabled": true,
                    "destOverride": [
                        "http",
                        "tls"
                    ],
                    "routeOnly": false
                },
                "settings": {
                    "auth": "noauth",
                    "udp": true,
                    "allowTransparent": false
                }
            }
        ],
        "remarks": "Germany: || Hetzner Online GmbH"
    },
    {
        "log": {
            "access": "",
            "error": "",
            "loglevel": "warning"
        },
        "outbounds": [
            {
                "tag": "proxy",
                "protocol": "vless",
                "settings": {
                    "vnext": [
                        {
                            "address": "\n<html><head>\n<meta http-equiv=\"content-type\" content=\"text/html;charset=utf-8\">\n<title>403 Forbidden</title>\n</head>\n<body text=#000000 bgcolor=#ffffff>\n<h1>Error: Forbidden</h1>\n<h2>Your client does not have permission to get URL <code>/api/</code> from this server.</h2>\n<h2></h2>\n</body></html>\n",
                            "port": 443,
                            "users": [
                                {
                                    "id": "fa72a38c-56bf-4f3b-9735-e96e9840ae54",
                                    "alterId": 0,
                                    "email": "t@t.tt",
                                    "security": "auto",
                                    "encryption": "none",
                                    "flow": ""
                                }
                            ]
                        }
                    ]
                },
                "streamSettings": {
                    "network": "tcp",
                    "security": "tls",
                    "tlsSettings": {
                        "allowInsecure": true,
                        "serverName": "app.chandplus.com",
                        "alpn": [
                            "http/1.1",
                            "h2",
                            "h3"
                        ],
                        "show": false
                    }
                },
                "mux": {
                    "enabled": false,
                    "concurrency": -1
                }
            },
            {
                "tag": "direct",
                "protocol": "freedom",
                "settings": {}
            },
            {
                "tag": "block",
                "protocol": "blackhole",
                "settings": {
                    "response": {
                        "type": "http"
                    }
                }
            }
        ],
        "inbounds": [
            {
                "tag": "socks",
                "port": 10808,
                "listen": "127.0.0.1",
                "protocol": "socks",
                "sniffing": {
                    "enabled": true,
                    "destOverride": [
                        "http",
                        "tls"
                    ],
                    "routeOnly": false
                },
                "settings": {
                    "auth": "noauth",
                    "udp": true,
                    "allowTransparent": false
                }
            },
            {
                "tag": "http",
                "port": 10809,
                "listen": "127.0.0.1",
                "protocol": "http",
                "sniffing": {
                    "enabled": true,
                    "destOverride": [
                        "http",
                        "tls"
                    ],
                    "routeOnly": false
                },
                "settings": {
                    "auth": "noauth",
                    "udp": true,
                    "allowTransparent": false
                }
            }
        ],
        "remarks": "Finland: || Hetzner Online GmbH"
    },
    {
        "log": {
            "access": "",
            "error": "",
            "loglevel": "warning"
        },
        "outbounds": [
            {
                "tag": "proxy",
                "protocol": "vless",
                "settings": {
                    "vnext": [
                        {
                            "address": "2a01:4f8:c012:bbe3::1",
                            "port": 443,
                            "users": [
                                {
                                    "id": "04bb5055-bc44-4d21-85c7-42317dd5fd37",
                                    "alterId": 0,
                                    "email": "t@t.tt",
                                    "security": "auto",
                                    "encryption": "none",
                                    "flow": ""
                                }
                            ]
                        }
                    ]
                },
                "streamSettings": {
                    "network": "tcp",
                    "tcpSettings": {
                        "header": {
                            "type": "http",
                            "request": {
                                "version": "1.1",
                                "method": "GET",
                                "path": [
                                    "/"
                                ],
                                "headers": {
                                    "Host": [
                                        "zula.ir"
                                    ],
                                    "User-Agent": [
                                        ""
                                    ],
                                    "Accept-Encoding": [
                                        "gzip, deflate"
                                    ],
                                    "Connection": [
                                        "keep-alive"
                                    ],
                                    "Pragma": "no-cache"
                                }
                            }
                        }
                    }
                },
                "mux": {
                    "enabled": false,
                    "concurrency": -1
                }
            },
            {
                "tag": "direct",
                "protocol": "freedom",
                "settings": {}
            },
            {
                "tag": "block",
                "protocol": "blackhole",
                "settings": {
                    "response": {
                        "type": "http"
                    }
                }
            }
        ],
        "inbounds": [
            {
                "tag": "socks",
                "port": 10808,
                "listen": "127.0.0.1",
                "protocol": "socks",
                "sniffing": {
                    "enabled": true,
                    "destOverride": [
                        "http",
                        "tls"
                    ],
                    "routeOnly": false
                },
                "settings": {
                    "auth": "noauth",
                    "udp": true,
                    "allowTransparent": false
                }
            },
            {
                "tag": "http",
                "port": 10809,
                "listen": "127.0.0.1",
                "protocol": "http",
                "sniffing": {
                    "enabled": true,
                    "destOverride": [
                        "http",
                        "tls"
                    ],
                    "routeOnly": false
                },
                "settings": {
                    "auth": "noauth",
                    "udp": true,
                    "allowTransparent": false
                }
            }
        ],
        "remarks": "Iran: || Parsonline"
    },
    {
        "log": {
            "access": "",
            "error": "",
            "loglevel": "warning"
        },
        "outbounds": [
            {
                "tag": "proxy",
                "protocol": "vless",
                "settings": {
                    "vnext": [
                        {
                            "address": "2600:3c04::2000:14ff:fea1:7115",
                            "port": 80,
                            "users": [
                                {
                                    "id": "07d0914a-f398-48d6-bc2c-3e23d1569623",
                                    "alterId": 0,
                                    "email": "t@t.tt",
                                    "security": "auto",
                                    "encryption": "none",
                                    "flow": ""
                                }
                            ]
                        }
                    ]
                },
                "streamSettings": {
                    "network": "ws",
                    "wsSettings": {
                        "path": "/?ed=2048",
                        "headers": {
                            "Host": "FAMoUS-BlOoD.ONeEaT.co."
                        }
                    }
                },
                "mux": {
                    "enabled": false,
                    "concurrency": -1
                }
            },
            {
                "tag": "direct",
                "protocol": "freedom",
                "settings": {}
            },
            {
                "tag": "block",
                "protocol": "blackhole",
                "settings": {
                    "response": {
                        "type": "http"
                    }
                }
            }
        ],
        "inbounds": [
            {
                "tag": "socks",
                "port": 10808,
                "listen": "127.0.0.1",
                "protocol": "socks",
                "sniffing": {
                    "enabled": true,
                    "destOverride": [
                        "http",
                        "tls"
                    ],
                    "routeOnly": false
                },
                "settings": {
                    "auth": "noauth",
                    "udp": true,
                    "allowTransparent": false
                }
            },
            {
                "tag": "http",
                "port": 10809,
                "listen": "127.0.0.1",
                "protocol": "http",
                "sniffing": {
                    "enabled": true,
                    "destOverride": [
                        "http",
                        "tls"
                    ],
                    "routeOnly": false
                },
                "settings": {
                    "auth": "noauth",
                    "udp": true,
                    "allowTransparent": false
                }
            }
        ],
        "remarks": "Canada: || Akamai Technologies"
    },
    {
        "log": {
            "access": "",
            "error": "",
            "loglevel": "warning"
        },
        "outbounds": [
            {
                "tag": "proxy",
                "protocol": "vless",
                "settings": {
                    "vnext": [
                        {
                            "address": "2604:2dc0:101:200::49d0",
                            "port": 443,
                            "users": [
                                {
                                    "id": "0fbecce1-acf9-4b6e-a0f7-f48be9d2b7d0",
                                    "alterId": 0,
                                    "email": "t@t.tt",
                                    "security": "auto",
                                    "encryption": "none",
                                    "flow": ""
                                }
                            ]
                        }
                    ]
                },
                "streamSettings": {
                    "network": "ws",
                    "wsSettings": {
                        "path": "/linkws?ed=2560",
                        "headers": {
                            "Host": "MAxNETvipAp-cloUD252.nEtKh3.site"
                        }
                    },
                    "security": "tls",
                    "tlsSettings": {
                        "allowInsecure": true,
                        "serverName": "MAxNETvipAp-cloUD252.nEtKh3.site",
                        "alpn": []
                    }
                },
                "mux": {
                    "enabled": false,
                    "concurrency": -1
                }
            },
            {
                "tag": "direct",
                "protocol": "freedom",
                "settings": {}
            },
            {
                "tag": "block",
                "protocol": "blackhole",
                "settings": {
                    "response": {
                        "type": "http"
                    }
                }
            }
        ],
        "inbounds": [
            {
                "tag": "socks",
                "port": 10808,
                "listen": "127.0.0.1",
                "protocol": "socks",
                "sniffing": {
                    "enabled": true,
                    "destOverride": [
                        "http",
                        "tls"
                    ],
                    "routeOnly": false
                },
                "settings": {
                    "auth": "noauth",
                    "udp": true,
                    "allowTransparent": false
                }
            },
            {
                "tag": "http",
                "port": 10809,
                "listen": "127.0.0.1",
                "protocol": "http",
                "sniffing": {
                    "enabled": true,
                    "destOverride": [
                        "http",
                        "tls"
                    ],
                    "routeOnly": false
                },
                "settings": {
                    "auth": "noauth",
                    "udp": true,
                    "allowTransparent": false
                }
            }
        ],
        "remarks": "United States: || OVH SAS"
    },
    {
        "log": {
            "access": "",
            "error": "",
            "loglevel": "warning"
        },
        "outbounds": [
            {
                "tag": "proxy",
                "protocol": "vless",
                "settings": {
                    "vnext": [
                        {
                            "address": "2a01:4f8:1c1b:10ec::1",
                            "port": 80,
                            "users": [
                                {
                                    "id": "1523920e-b41f-42d9-970e-6f672b56f025",
                                    "alterId": 0,
                                    "email": "t@t.tt",
                                    "security": "auto",
                                    "encryption": "none",
                                    "flow": ""
                                }
                            ]
                        }
                    ]
                },
                "streamSettings": {
                    "network": "httpupgrade",
                    "httpupgradeSettings": {
                        "path": "/telegram,@BINEXTIFY-telegram,@BINEXTIFY-telegram,@BINEXTIFY-telegram,@BINEXTIFY-telegram,@BINEXTIFY-telegram,@BINEXTIFY-telegram,@BINEXTIFY-telegram,@BINEXTIFY-telegram,@BINEXTIFY?ed=2560",
                        "host": "www.spEedtest.net.jariCopEn.fuN."
                    },
                    "security": "",
                    "tlsSettings": {
                        "tlsSettings": {
                            "allowInsecure": true,
                            "serverName": "",
                            "alpn": []
                        }
                    }
                },
                "mux": {
                    "enabled": false,
                    "concurrency": -1
                }
            },
            {
                "tag": "direct",
                "protocol": "freedom",
                "settings": {}
            },
            {
                "tag": "block",
                "protocol": "blackhole",
                "settings": {
                    "response": {
                        "type": "http"
                    }
                }
            }
        ],
        "inbounds": [
            {
                "tag": "socks",
                "port": 10808,
                "listen": "127.0.0.1",
                "protocol": "socks",
                "sniffing": {
                    "enabled": true,
                    "destOverride": [
                        "http",
                        "tls"
                    ],
                    "routeOnly": false
                },
                "settings": {
                    "auth": "noauth",
                    "udp": true,
                    "allowTransparent": false
                }
            },
            {
                "tag": "http",
                "port": 10809,
                "listen": "127.0.0.1",
                "protocol": "http",
                "sniffing": {
                    "enabled": true,
                    "destOverride": [
                        "http",
                        "tls"
                    ],
                    "routeOnly": false
                },
                "settings": {
                    "auth": "noauth",
                    "udp": true,
                    "allowTransparent": false
                }
            }
        ],
        "remarks": "Germany: || Hetzner Online AG"
    },
    {
        "log": {
            "access": "",
            "error": "",
            "loglevel": "warning"
        },
        "outbounds": [
            {
                "tag": "proxy",
                "protocol": "vless",
                "settings": {
                    "vnext": [
                        {
                            "address": "2a01:4f8:1c1b:1914::1",
                            "port": 443,
                            "users": [
                                {
                                    "id": "33707040-edcf-4185-94e4-2a071315c602",
                                    "alterId": 0,
                                    "email": "t@t.tt",
                                    "security": "auto",
                                    "encryption": "none",
                                    "flow": ""
                                }
                            ]
                        }
                    ]
                },
                "streamSettings": {
                    "network": "tcp",
                    "security": "reality",
                    "realitySettings": {
                        "serverName": "vpn_proxy_channel_vpn_proxy_channel.hohod.ir",
                        "fingerprint": "chrome",
                        "show": false,
                        "publicKey": "GpgfsA-U8Y8M3LRcTfsaBViDtp2VlN5riSLLZ2kxEiQ",
                        "shortId": "7def4dde",
                        "spiderX": ""
                    }
                },
                "mux": {
                    "enabled": false,
                    "concurrency": -1
                }
            },
            {
                "tag": "direct",
                "protocol": "freedom",
                "settings": {}
            },
            {
                "tag": "block",
                "protocol": "blackhole",
                "settings": {
                    "response": {
                        "type": "http"
                    }
                }
            }
        ],
        "inbounds": [
            {
                "tag": "socks",
                "port": 10808,
                "listen": "127.0.0.1",
                "protocol": "socks",
                "sniffing": {
                    "enabled": true,
                    "destOverride": [
                        "http",
                        "tls"
                    ],
                    "routeOnly": false
                },
                "settings": {
                    "auth": "noauth",
                    "udp": true,
                    "allowTransparent": false
                }
            },
            {
                "tag": "http",
                "port": 10809,
                "listen": "127.0.0.1",
                "protocol": "http",
                "sniffing": {
                    "enabled": true,
                    "destOverride": [
                        "http",
                        "tls"
                    ],
                    "routeOnly": false
                },
                "settings": {
                    "auth": "noauth",
                    "udp": true,
                    "allowTransparent": false
                }
            }
        ],
        "remarks": "Germany: || Hetzner Online GmbH"
    },
    {
        "log": {
            "access": "",
            "error": "",
            "loglevel": "warning"
        },
        "outbounds": [
            {
                "tag": "proxy",
                "protocol": "vless",
                "settings": {
                    "vnext": [
                        {
                            "address": "2a0c:16c2:500:12f::2598",
                            "port": 443,
                            "users": [
                                {
                                    "id": "65106492-519f-40e7-97e3-c8ae1ff181b5",
                                    "alterId": 0,
                                    "email": "t@t.tt",
                                    "security": "auto",
                                    "encryption": "none",
                                    "flow": "xtls-rprx-vision"
                                }
                            ]
                        }
                    ]
                },
                "streamSettings": {
                    "network": "tcp",
                    "security": "reality",
                    "realitySettings": {
                        "serverName": "telegram.org",
                        "fingerprint": "chrome",
                        "show": false,
                        "publicKey": "rinBDKTub2XJCCgxEpNkJm195JhZpk1JJxMibyJhWCA",
                        "shortId": "d11c051042256944",
                        "spiderX": "/"
                    }
                },
                "mux": {
                    "enabled": false,
                    "concurrency": -1
                }
            },
            {
                "tag": "direct",
                "protocol": "freedom",
                "settings": {}
            },
            {
                "tag": "block",
                "protocol": "blackhole",
                "settings": {
                    "response": {
                        "type": "http"
                    }
                }
            }
        ],
        "inbounds": [
            {
                "tag": "socks",
                "port": 10808,
                "listen": "127.0.0.1",
                "protocol": "socks",
                "sniffing": {
                    "enabled": true,
                    "destOverride": [
                        "http",
                        "tls"
                    ],
                    "routeOnly": false
                },
                "settings": {
                    "auth": "noauth",
                    "udp": true,
                    "allowTransparent": false
                }
            },
            {
                "tag": "http",
                "port": 10809,
                "listen": "127.0.0.1",
                "protocol": "http",
                "sniffing": {
                    "enabled": true,
                    "destOverride": [
                        "http",
                        "tls"
                    ],
                    "routeOnly": false
                },
                "settings": {
                    "auth": "noauth",
                    "udp": true,
                    "allowTransparent": false
                }
            }
        ],
        "remarks": "Netherlands: || SIA VEESP"
    },
    {
        "log": {
            "access": "",
            "error": "",
            "loglevel": "warning"
        },
        "outbounds": [
            {
                "tag": "proxy",
                "protocol": "vless",
                "settings": {
                    "vnext": [
                        {
                            "address": "\n<html><head>\n<meta http-equiv=\"content-type\" content=\"text/html;charset=utf-8\">\n<title>403 Forbidden</title>\n</head>\n<body text=#000000 bgcolor=#ffffff>\n<h1>Error: Forbidden</h1>\n<h2>Your client does not have permission to get URL <code>/api/</code> from this server.</h2>\n<h2></h2>\n</body></html>\n",
                            "port": 6969,
                            "users": [
                                {
                                    "id": "83f79baf-b03f-4fa3-be3e-f32ae64142a0",
                                    "alterId": 0,
                                    "email": "t@t.tt",
                                    "security": "auto",
                                    "encryption": "none",
                                    "flow": ""
                                }
                            ]
                        }
                    ]
                },
                "streamSettings": {
                    "network": "tcp",
                    "tcpSettings": {
                        "header": {
                            "type": "http",
                            "request": {
                                "version": "1.1",
                                "method": "GET",
                                "path": [
                                    "/"
                                ],
                                "headers": {
                                    "Host": [
                                        "---@External_Net---@External_Net---@External_Net---@External_Net---@External_Net"
                                    ],
                                    "User-Agent": [
                                        ""
                                    ],
                                    "Accept-Encoding": [
                                        "gzip, deflate"
                                    ],
                                    "Connection": [
                                        "keep-alive"
                                    ],
                                    "Pragma": "no-cache"
                                }
                            }
                        }
                    }
                },
                "mux": {
                    "enabled": false,
                    "concurrency": -1
                }
            },
            {
                "tag": "direct",
                "protocol": "freedom",
                "settings": {}
            },
            {
                "tag": "block",
                "protocol": "blackhole",
                "settings": {
                    "response": {
                        "type": "http"
                    }
                }
            }
        ],
        "inbounds": [
            {
                "tag": "socks",
                "port": 10808,
                "listen": "127.0.0.1",
                "protocol": "socks",
                "sniffing": {
                    "enabled": true,
                    "destOverride": [
                        "http",
                        "tls"
                    ],
                    "routeOnly": false
                },
                "settings": {
                    "auth": "noauth",
                    "udp": true,
                    "allowTransparent": false
                }
            },
            {
                "tag": "http",
                "port": 10809,
                "listen": "127.0.0.1",
                "protocol": "http",
                "sniffing": {
                    "enabled": true,
                    "destOverride": [
                        "http",
                        "tls"
                    ],
                    "routeOnly": false
                },
                "settings": {
                    "auth": "noauth",
                    "udp": true,
                    "allowTransparent": false
                }
            }
        ],
        "remarks": "Germany: || Hetzner Online GmbH"
    },
    {
        "log": {
            "access": "",
            "error": "",
            "loglevel": "warning"
        },
        "outbounds": [
            {
                "tag": "proxy",
                "protocol": "vless",
                "settings": {
                    "vnext": [
                        {
                            "address": "2a01:4f8:c013:cb9f::1",
                            "port": 443,
                            "users": [
                                {
                                    "id": "9a85ea24-bd5a-4380-94cb-ffb773cafb33",
                                    "alterId": 0,
                                    "email": "t@t.tt",
                                    "security": "auto",
                                    "encryption": "none",
                                    "flow": ""
                                }
                            ]
                        }
                    ]
                },
                "streamSettings": {
                    "network": "tcp",
                    "tcpSettings": {
                        "header": {
                            "type": "http",
                            "request": {
                                "version": "1.1",
                                "method": "GET",
                                "path": [
                                    "/"
                                ],
                                "headers": {
                                    "Host": [
                                        "zula.ir"
                                    ],
                                    "User-Agent": [
                                        ""
                                    ],
                                    "Accept-Encoding": [
                                        "gzip, deflate"
                                    ],
                                    "Connection": [
                                        "keep-alive"
                                    ],
                                    "Pragma": "no-cache"
                                }
                            }
                        }
                    }
                },
                "mux": {
                    "enabled": false,
                    "concurrency": -1
                }
            },
            {
                "tag": "direct",
                "protocol": "freedom",
                "settings": {}
            },
            {
                "tag": "block",
                "protocol": "blackhole",
                "settings": {
                    "response": {
                        "type": "http"
                    }
                }
            }
        ],
        "inbounds": [
            {
                "tag": "socks",
                "port": 10808,
                "listen": "127.0.0.1",
                "protocol": "socks",
                "sniffing": {
                    "enabled": true,
                    "destOverride": [
                        "http",
                        "tls"
                    ],
                    "routeOnly": false
                },
                "settings": {
                    "auth": "noauth",
                    "udp": true,
                    "allowTransparent": false
                }
            },
            {
                "tag": "http",
                "port": 10809,
                "listen": "127.0.0.1",
                "protocol": "http",
                "sniffing": {
                    "enabled": true,
                    "destOverride": [
                        "http",
                        "tls"
                    ],
                    "routeOnly": false
                },
                "settings": {
                    "auth": "noauth",
                    "udp": true,
                    "allowTransparent": false
                }
            }
        ],
        "remarks": "Germany: || Hetzner Online GmbH"
    },
    {
        "log": {
            "access": "",
            "error": "",
            "loglevel": "warning"
        },
        "outbounds": [
            {
                "tag": "proxy",
                "protocol": "vless",
                "settings": {
                    "vnext": [
                        {
                            "address": "2a01:4f8:1c17:c62e::1",
                            "port": 45489,
                            "users": [
                                {
                                    "id": "a6a88377-8e73-42e9-bf9e-29e04a3cc949",
                                    "alterId": 0,
                                    "email": "t@t.tt",
                                    "security": "auto",
                                    "encryption": "none",
                                    "flow": ""
                                }
                            ]
                        }
                    ]
                },
                "streamSettings": {
                    "network": "tcp",
                    "tcpSettings": {
                        "header": {
                            "type": "http",
                            "request": {
                                "version": "1.1",
                                "method": "GET",
                                "path": [
                                    "/"
                                ],
                                "headers": {
                                    "Host": [
                                        "speedtest.net"
                                    ],
                                    "User-Agent": [
                                        ""
                                    ],
                                    "Accept-Encoding": [
                                        "gzip, deflate"
                                    ],
                                    "Connection": [
                                        "keep-alive"
                                    ],
                                    "Pragma": "no-cache"
                                }
                            }
                        }
                    }
                },
                "mux": {
                    "enabled": false,
                    "concurrency": -1
                }
            },
            {
                "tag": "direct",
                "protocol": "freedom",
                "settings": {}
            },
            {
                "tag": "block",
                "protocol": "blackhole",
                "settings": {
                    "response": {
                        "type": "http"
                    }
                }
            }
        ],
        "inbounds": [
            {
                "tag": "socks",
                "port": 10808,
                "listen": "127.0.0.1",
                "protocol": "socks",
                "sniffing": {
                    "enabled": true,
                    "destOverride": [
                        "http",
                        "tls"
                    ],
                    "routeOnly": false
                },
                "settings": {
                    "auth": "noauth",
                    "udp": true,
                    "allowTransparent": false
                }
            },
            {
                "tag": "http",
                "port": 10809,
                "listen": "127.0.0.1",
                "protocol": "http",
                "sniffing": {
                    "enabled": true,
                    "destOverride": [
                        "http",
                        "tls"
                    ],
                    "routeOnly": false
                },
                "settings": {
                    "auth": "noauth",
                    "udp": true,
                    "allowTransparent": false
                }
            }
        ],
        "remarks": "Germany: || Hetzner Online AG"
    },
    {
        "log": {
            "access": "",
            "error": "",
            "loglevel": "warning"
        },
        "outbounds": [
            {
                "tag": "proxy",
                "protocol": "vless",
                "settings": {
                    "vnext": [
                        {
                            "address": "2a0c:16c2:500:213::6ae3",
                            "port": 28202,
                            "users": [
                                {
                                    "id": "a850cac7-9264-449b-8ca4-33118ebbc6e0",
                                    "alterId": 0,
                                    "email": "t@t.tt",
                                    "security": "auto",
                                    "encryption": "none",
                                    "flow": "xtls-rprx-vision"
                                }
                            ]
                        }
                    ]
                },
                "streamSettings": {
                    "network": "tcp",
                    "security": "reality",
                    "realitySettings": {
                        "serverName": "dns-shop.ru",
                        "fingerprint": "chrome",
                        "show": false,
                        "publicKey": "Z8s87Dp6qlWDkGUorxH6W7Pnstcdo3M7ZDS3thi4dh0",
                        "shortId": "8f03a19272d0c09d",
                        "spiderX": "/"
                    }
                },
                "mux": {
                    "enabled": false,
                    "concurrency": -1
                }
            },
            {
                "tag": "direct",
                "protocol": "freedom",
                "settings": {}
            },
            {
                "tag": "block",
                "protocol": "blackhole",
                "settings": {
                    "response": {
                        "type": "http"
                    }
                }
            }
        ],
        "inbounds": [
            {
                "tag": "socks",
                "port": 10808,
                "listen": "127.0.0.1",
                "protocol": "socks",
                "sniffing": {
                    "enabled": true,
                    "destOverride": [
                        "http",
                        "tls"
                    ],
                    "routeOnly": false
                },
                "settings": {
                    "auth": "noauth",
                    "udp": true,
                    "allowTransparent": false
                }
            },
            {
                "tag": "http",
                "port": 10809,
                "listen": "127.0.0.1",
                "protocol": "http",
                "sniffing": {
                    "enabled": true,
                    "destOverride": [
                        "http",
                        "tls"
                    ],
                    "routeOnly": false
                },
                "settings": {
                    "auth": "noauth",
                    "udp": true,
                    "allowTransparent": false
                }
            }
        ],
        "remarks": "Netherlands: || SIA VEESP"
    },
    {
        "log": {
            "access": "",
            "error": "",
            "loglevel": "warning"
        },
        "outbounds": [
            {
                "tag": "proxy",
                "protocol": "vless",
                "settings": {
                    "vnext": [
                        {
                            "address": "2a0c:16c2:500:213::6ae3",
                            "port": 28202,
                            "users": [
                                {
                                    "id": "d2115b2e-8fa3-4897-bb7c-ff9556e3190b",
                                    "alterId": 0,
                                    "email": "t@t.tt",
                                    "security": "auto",
                                    "encryption": "none",
                                    "flow": "xtls-rprx-vision"
                                }
                            ]
                        }
                    ]
                },
                "streamSettings": {
                    "network": "tcp",
                    "security": "reality",
                    "realitySettings": {
                        "serverName": "dns-shop.ru",
                        "fingerprint": "chrome",
                        "show": false,
                        "publicKey": "Z8s87Dp6qlWDkGUorxH6W7Pnstcdo3M7ZDS3thi4dh0",
                        "shortId": "8f03a19272d0c09d",
                        "spiderX": "/"
                    }
                },
                "mux": {
                    "enabled": false,
                    "concurrency": -1
                }
            },
            {
                "tag": "direct",
                "protocol": "freedom",
                "settings": {}
            },
            {
                "tag": "block",
                "protocol": "blackhole",
                "settings": {
                    "response": {
                        "type": "http"
                    }
                }
            }
        ],
        "inbounds": [
            {
                "tag": "socks",
                "port": 10808,
                "listen": "127.0.0.1",
                "protocol": "socks",
                "sniffing": {
                    "enabled": true,
                    "destOverride": [
                        "http",
                        "tls"
                    ],
                    "routeOnly": false
                },
                "settings": {
                    "auth": "noauth",
                    "udp": true,
                    "allowTransparent": false
                }
            },
            {
                "tag": "http",
                "port": 10809,
                "listen": "127.0.0.1",
                "protocol": "http",
                "sniffing": {
                    "enabled": true,
                    "destOverride": [
                        "http",
                        "tls"
                    ],
                    "routeOnly": false
                },
                "settings": {
                    "auth": "noauth",
                    "udp": true,
                    "allowTransparent": false
                }
            }
        ],
        "remarks": "Netherlands: || SIA VEESP"
    },
    {
        "log": {
            "access": "",
            "error": "",
            "loglevel": "warning"
        },
        "outbounds": [
            {
                "tag": "proxy",
                "protocol": "vless",
                "settings": {
                    "vnext": [
                        {
                            "address": "2a0b:4140:41f4::2",
                            "port": 22086,
                            "users": [
                                {
                                    "id": "df9de24d-8900-4f76-977d-c740dd748a8b",
                                    "alterId": 0,
                                    "email": "t@t.tt",
                                    "security": "auto",
                                    "encryption": "none",
                                    "flow": ""
                                }
                            ]
                        }
                    ]
                },
                "streamSettings": {
                    "network": "tcp",
                    "security": "reality",
                    "realitySettings": {
                        "serverName": "www.latimes.com",
                        "fingerprint": "chrome",
                        "show": false,
                        "publicKey": "YdiT9ol9m3lWJfarNH78NhxgZrWjFze-pBnKgd-Zyms",
                        "shortId": "23675e195a587c22",
                        "spiderX": "/@ConfigRayegan----"
                    }
                },
                "mux": {
                    "enabled": false,
                    "concurrency": -1
                }
            },
            {
                "tag": "direct",
                "protocol": "freedom",
                "settings": {}
            },
            {
                "tag": "block",
                "protocol": "blackhole",
                "settings": {
                    "response": {
                        "type": "http"
                    }
                }
            }
        ],
        "inbounds": [
            {
                "tag": "socks",
                "port": 10808,
                "listen": "127.0.0.1",
                "protocol": "socks",
                "sniffing": {
                    "enabled": true,
                    "destOverride": [
                        "http",
                        "tls"
                    ],
                    "routeOnly": false
                },
                "settings": {
                    "auth": "noauth",
                    "udp": true,
                    "allowTransparent": false
                }
            },
            {
                "tag": "http",
                "port": 10809,
                "listen": "127.0.0.1",
                "protocol": "http",
                "sniffing": {
                    "enabled": true,
                    "destOverride": [
                        "http",
                        "tls"
                    ],
                    "routeOnly": false
                },
                "settings": {
                    "auth": "noauth",
                    "udp": true,
                    "allowTransparent": false
                }
            }
        ],
        "remarks": "Germany: || Aeza International LTD"
    },
    {
        "log": {
            "access": "",
            "error": "",
            "loglevel": "warning"
        },
        "outbounds": [
            {
                "tag": "proxy",
                "protocol": "vless",
                "settings": {
                    "vnext": [
                        {
                            "address": "2a0c:16c2:500:12f::2598",
                            "port": 443,
                            "users": [
                                {
                                    "id": "e20a3f6e-f30d-4191-a042-429e6bfb8598",
                                    "alterId": 0,
                                    "email": "t@t.tt",
                                    "security": "auto",
                                    "encryption": "none",
                                    "flow": "xtls-rprx-vision"
                                }
                            ]
                        }
                    ]
                },
                "streamSettings": {
                    "network": "tcp",
                    "security": "reality",
                    "realitySettings": {
                        "serverName": "telegram.org",
                        "fingerprint": "chrome",
                        "show": false,
                        "publicKey": "rinBDKTub2XJCCgxEpNkJm195JhZpk1JJxMibyJhWCA",
                        "shortId": "d11c051042256944",
                        "spiderX": "/"
                    }
                },
                "mux": {
                    "enabled": false,
                    "concurrency": -1
                }
            },
            {
                "tag": "direct",
                "protocol": "freedom",
                "settings": {}
            },
            {
                "tag": "block",
                "protocol": "blackhole",
                "settings": {
                    "response": {
                        "type": "http"
                    }
                }
            }
        ],
        "inbounds": [
            {
                "tag": "socks",
                "port": 10808,
                "listen": "127.0.0.1",
                "protocol": "socks",
                "sniffing": {
                    "enabled": true,
                    "destOverride": [
                        "http",
                        "tls"
                    ],
                    "routeOnly": false
                },
                "settings": {
                    "auth": "noauth",
                    "udp": true,
                    "allowTransparent": false
                }
            },
            {
                "tag": "http",
                "port": 10809,
                "listen": "127.0.0.1",
                "protocol": "http",
                "sniffing": {
                    "enabled": true,
                    "destOverride": [
                        "http",
                        "tls"
                    ],
                    "routeOnly": false
                },
                "settings": {
                    "auth": "noauth",
                    "udp": true,
                    "allowTransparent": false
                }
            }
        ],
        "remarks": "Netherlands: || SIA VEESP"
    },
    {
        "log": {
            "access": "",
            "error": "",
            "loglevel": "warning"
        },
        "outbounds": [
            {
                "tag": "proxy",
                "protocol": "vless",
                "settings": {
                    "vnext": [
                        {
                            "address": "2a01:4f8:1c1b:2cfc::1",
                            "port": 80,
                            "users": [
                                {
                                    "id": "e8918c01-95da-41dc-ac23-94f33481a475",
                                    "alterId": 0,
                                    "email": "t@t.tt",
                                    "security": "auto",
                                    "encryption": "none",
                                    "flow": ""
                                }
                            ]
                        }
                    ]
                },
                "streamSettings": {
                    "network": "ws",
                    "wsSettings": {
                        "path": "/@V2rayNGcloud---Telegram---v2rayNGcloud---@V2rayNGcloud---Telegram---@V2rayNGcloud---Telegram---@V2rayNGcloud---@V2rayNGcloud---Telegram---v2rayNGcloud---@V2rayNGcloud---Telegram---@V2rayNGcloud---Telegram---@V2rayNGcloud?ed=2087",
                        "headers": {
                            "Host": "amiri2.server-dev2.ir"
                        }
                    }
                },
                "mux": {
                    "enabled": false,
                    "concurrency": -1
                }
            },
            {
                "tag": "direct",
                "protocol": "freedom",
                "settings": {}
            },
            {
                "tag": "block",
                "protocol": "blackhole",
                "settings": {
                    "response": {
                        "type": "http"
                    }
                }
            }
        ],
        "inbounds": [
            {
                "tag": "socks",
                "port": 10808,
                "listen": "127.0.0.1",
                "protocol": "socks",
                "sniffing": {
                    "enabled": true,
                    "destOverride": [
                        "http",
                        "tls"
                    ],
                    "routeOnly": false
                },
                "settings": {
                    "auth": "noauth",
                    "udp": true,
                    "allowTransparent": false
                }
            },
            {
                "tag": "http",
                "port": 10809,
                "listen": "127.0.0.1",
                "protocol": "http",
                "sniffing": {
                    "enabled": true,
                    "destOverride": [
                        "http",
                        "tls"
                    ],
                    "routeOnly": false
                },
                "settings": {
                    "auth": "noauth",
                    "udp": true,
                    "allowTransparent": false
                }
            }
        ],
        "remarks": "Germany: || Hetzner Online AG"
    },
    {
        "log": {
            "access": "",
            "error": "",
            "loglevel": "warning"
        },
        "outbounds": [
            {
                "tag": "proxy",
                "protocol": "vless",
                "settings": {
                    "vnext": [
                        {
                            "address": "2a0c:16c2:500:213::6ae3",
                            "port": 28202,
                            "users": [
                                {
                                    "id": "fa781916-aee3-4693-b88f-d623d54d45f2",
                                    "alterId": 0,
                                    "email": "t@t.tt",
                                    "security": "auto",
                                    "encryption": "none",
                                    "flow": "xtls-rprx-vision"
                                }
                            ]
                        }
                    ]
                },
                "streamSettings": {
                    "network": "tcp",
                    "security": "reality",
                    "realitySettings": {
                        "serverName": "dns-shop.ru",
                        "fingerprint": "chrome",
                        "show": false,
                        "publicKey": "Z8s87Dp6qlWDkGUorxH6W7Pnstcdo3M7ZDS3thi4dh0",
                        "shortId": "8f03a19272d0c09d",
                        "spiderX": "/"
                    }
                },
                "mux": {
                    "enabled": false,
                    "concurrency": -1
                }
            },
            {
                "tag": "direct",
                "protocol": "freedom",
                "settings": {}
            },
            {
                "tag": "block",
                "protocol": "blackhole",
                "settings": {
                    "response": {
                        "type": "http"
                    }
                }
            }
        ],
        "inbounds": [
            {
                "tag": "socks",
                "port": 10808,
                "listen": "127.0.0.1",
                "protocol": "socks",
                "sniffing": {
                    "enabled": true,
                    "destOverride": [
                        "http",
                        "tls"
                    ],
                    "routeOnly": false
                },
                "settings": {
                    "auth": "noauth",
                    "udp": true,
                    "allowTransparent": false
                }
            },
            {
                "tag": "http",
                "port": 10809,
                "listen": "127.0.0.1",
                "protocol": "http",
                "sniffing": {
                    "enabled": true,
                    "destOverride": [
                        "http",
                        "tls"
                    ],
                    "routeOnly": false
                },
                "settings": {
                    "auth": "noauth",
                    "udp": true,
                    "allowTransparent": false
                }
            }
        ],
        "remarks": "Netherlands: || SIA VEESP"
    },
    {
        "log": {
            "access": "",
            "error": "",
            "loglevel": "warning"
        },
        "outbounds": [
            {
                "tag": "proxy",
                "protocol": "vless",
                "settings": {
                    "vnext": [
                        {
                            "address": "2a0b:4140:509c::2",
                            "port": 80,
                            "users": [
                                {
                                    "id": "fb29e858-0aee-44c5-8a57-57f7b797c16e",
                                    "alterId": 0,
                                    "email": "t@t.tt",
                                    "security": "auto",
                                    "encryption": "none",
                                    "flow": ""
                                }
                            ]
                        }
                    ]
                },
                "streamSettings": {
                    "network": "tcp",
                    "security": "reality",
                    "realitySettings": {
                        "serverName": "www.latimes.com",
                        "fingerprint": "chrome",
                        "show": false,
                        "publicKey": "bwoJ6SyPEsQ--wHp8WTUNTqe3FG9Vb0H8qJ2HHtmLGY",
                        "shortId": "e2",
                        "spiderX": "/@MdVpnSec----@MdVpnSec----@MdVpnSec----@MdVpnSec----@MdVpnSec----@MdVpnSec----@MdVpnSec----@MdVpnSec----@MdVpnSec----@MdVpnSec----@MdVpnSec----@MdVpnSec"
                    }
                },
                "mux": {
                    "enabled": false,
                    "concurrency": -1
                }
            },
            {
                "tag": "direct",
                "protocol": "freedom",
                "settings": {}
            },
            {
                "tag": "block",
                "protocol": "blackhole",
                "settings": {
                    "response": {
                        "type": "http"
                    }
                }
            }
        ],
        "inbounds": [
            {
                "tag": "socks",
                "port": 10808,
                "listen": "127.0.0.1",
                "protocol": "socks",
                "sniffing": {
                    "enabled": true,
                    "destOverride": [
                        "http",
                        "tls"
                    ],
                    "routeOnly": false
                },
                "settings": {
                    "auth": "noauth",
                    "udp": true,
                    "allowTransparent": false
                }
            },
            {
                "tag": "http",
                "port": 10809,
                "listen": "127.0.0.1",
                "protocol": "http",
                "sniffing": {
                    "enabled": true,
                    "destOverride": [
                        "http",
                        "tls"
                    ],
                    "routeOnly": false
                },
                "settings": {
                    "auth": "noauth",
                    "udp": true,
                    "allowTransparent": false
                }
            }
        ],
        "remarks": "France: || xorek.cloud International LTD"
    }
]